<?xml version="1.0" encoding="UTF-8"?>
<gvq:GVQ_Metadata xmlns:updated19115="http://www.geoviqua.org/19115_updates" xmlns:xlink="http://www.w3.org/1999/xlink" xmlns:xsi="http://www.w3.org/2001/XMLSchema-instance" xmlns:gmd="http://www.isotc211.org/2005/gmd" xmlns:gco="http://www.isotc211.org/2005/gco" xmlns:gvq="http://www.geoviqua.org/QualityInformationModel/4.0" xmlns:gml="http://www.opengis.net/gml/3.2" xmlns:gmd19157="http://www.geoviqua.org/gmd19157" xsi:schemaLocation="http://www.geoviqua.org/QualityInformationModel/4.0 http://schemas.geoviqua.org/GVQ/4.0/GeoViQua_PQM_UQM.xsd http://www.uncertml.org/2.0 http://www.uncertml.org/uncertml.xsd">
		<gmd:fileIdentifier>
			<gco:CharacterString>a0027-88fd-11da-a88f-000d939bc5d8</gco:CharacterString>
		</gmd:fileIdentifier>
		<gmd:parentIdentifier>
			<gco:CharacterString />
		</gmd:parentIdentifier>
		<gmd:hierarchyLevel>
			<gmd:MD_ScopeCode codeList="http://www.isotc211.org/2005/resources/codeList.xml#MD_ScopeCode" codeListValue="series">series</gmd:MD_ScopeCode>
		</gmd:hierarchyLevel>
		<gmd:contact>
			<gmd:CI_ResponsibleParty>
				<gmd:organisationName>
					<gco:CharacterString>NASA</gco:CharacterString>
				</gmd:organisationName>
				<gmd:role>
					<gmd:CI_RoleCode codeList="" codeListValue="originator" />
				</gmd:role>
			</gmd:CI_ResponsibleParty>
		</gmd:contact>
		<gmd:dateStamp>
			<gco:Date>1976-01-01</gco:Date>
		</gmd:dateStamp>
		<gmd:metadataStandardName>
			<gco:CharacterString>ISO 19115:2003/19139</gco:CharacterString>
		</gmd:metadataStandardName>
		<gmd:metadataStandardVersion>
			<gco:CharacterString>1.0</gco:CharacterString>
		</gmd:metadataStandardVersion>
		<gmd:identificationInfo>
			<gmd:MD_DataIdentification>
				<gmd:abstract>
					<gco:CharacterString>The purpose of the SNF study was to improve our understanding of the relationship between remotely sensed observations and important biophysical parameters in the boreal forest. A key element of the experiment was the development of methodologies to measure forest stand characteristics to determine values of importance to both remote sensing and ecology. Parameters studied were biomass, leaf area index, above ground net primary productivity, bark area index and ground coverage by vegetation. Thirty two quaking aspen and thirty one black spruce sites were studied. Sites were chosen in uniform stands of aspen or spruce. The dominant species in the site constituted over 80 percent, and usually over 95 percent, of the total tree density and basal area. Aspen stands were chosen to represent the full range of age and stem density of essentially pure aspen, of nearly complete canopy closure, and greater than two meters in height. Spruce stands ranged from very sparse stands on bog sites, to dense, closed stands on more productive peatlands. Use of multiple plots within each site allowed estimation of the importance of spatial variation in stand parameters. Within each plot, all woody stems greater than two meters in height were recorded by species and the following dimensions were measured: diameter breast height, height of the tree, height of the first live branch, and depth of crown. For each plot, a two meter diameter subplot was defined at the center of each plot. Within this subplot, the percent of ground coverage by plants under one meter in height was determined by species. These data, averaged for the five plots in each site, are presented in the SNF Forest Understory Cover Data (Table) data set in tabular format, e.g. plant species with a count for that species at each site. The same data are presented in this data set (i.e., SNF Forest Understory Cover Data) but are arranged with a row for each species and site and a percent ground coverage for each combination.</gco:CharacterString>
				</gmd:abstract>
				<gmd:descriptiveKeywords>
					<gmd:MD_Keywords>
						<gmd:keyword>
							<gco:CharacterString>EARTH SCIENCE BIOSPHERE VEGETATION VEGETATION SPECIES; FIELD INVESTIGATION; ESIP EARTH SCIENCE INFORMATION PARTNERS PROGRAM; EOSDIS EARTH OBSERVING SYSTEM DATA INFORMATION SYSTEM; SUPERIOR NATIONAL FOREST; CWIC CEOS WGISS INTEGRATED CATALOG; Eosdis; BIOTA; ENGLISH;</gco:CharacterString>
						</gmd:keyword>
					</gmd:MD_Keywords>
				</gmd:descriptiveKeywords>
				<gmd:language />
				<gmd:topicCategory>
					<gmd:MD_TopicCategoryCode>feedRSSAlert</gmd:MD_TopicCategoryCode>
				</gmd:topicCategory>
				<gmd:extent>
					<gmd:EX_Extent>
						<gmd:geographicElement>
							<gmd:EX_GeographicBoundingBox>
								<gmd:westBoundLongitude>
									<gco:Decimal>-92.5057983398438</gco:Decimal>
								</gmd:westBoundLongitude>
								<gmd:eastBoundLongitude>
									<gco:Decimal>-91.7658004760742</gco:Decimal>
								</gmd:eastBoundLongitude>
								<gmd:southBoundLatitude>
									<gco:Decimal>47.6575012207031</gco:Decimal>
								</gmd:southBoundLatitude>
								<gmd:northBoundLatitude>
									<gco:Decimal>48.1697006225586</gco:Decimal>
								</gmd:northBoundLatitude>
							</gmd:EX_GeographicBoundingBox>
						</gmd:geographicElement>
					</gmd:EX_Extent>
				</gmd:extent>
			</gmd:MD_DataIdentification>
		</gmd:identificationInfo>
	<gmd:dataQualityInfo>
		<gmd:DQ_DataQuality>
			<gmd:scope>
				<gmd:DQ_Scope id="datasetScope">
					<gmd:level>
						<gmd:MD_ScopeCode codeList="http://www.isotc211.org/2005/resources/codeList.xml#MD_ScopeCode" codeListValue="dataset"/>
					</gmd:level>
				</gmd:DQ_Scope>
			</gmd:scope>
			<gmd:lineage>
				<gmd:LI_Lineage>
					<gmd:statement>
						<gco:CharacterString>The obtention of this GCP point is done though digitazing over Landsat images non geometrically corrected. The GCP set contains two kind of points, those used to fit the geometric correction and those used to test it. The final GCP point file includes for each point several attributes including X RMS of the point, Y RMS of the point, XY RMS of the point, Global fit/test X RMS, Global fit/test Y RMS, Global fit/test XY RMS, observed and predicted values and X,Y,Z UTM-31N-ED50 coordinates.</gco:CharacterString>
					</gmd:statement>
					<gmd:processStep>
						<gmd:LI_ProcessStep id="GCP_digitizing">
							<gmd:description>
								<gco:CharacterString>Digitazing of GCP over Landsat images non geometrically corrected. For each GCP the  X,Y,Z UTM-31N-ED50 coordinates are documented as attributes. Those UTM coordinates of the GCP are obtaind from orthophotomap. The GCP file includes two set of points, those manually identified GCPs that will be used to fit the model (33 points) and those automatically selected to test the equations fitting (243 points).</gco:CharacterString>
							</gmd:description>
							<gmd:source>
								<gmd:LI_Source id="Landsat_image">
									<gmd:description>
										<gco:CharacterString>Seven bands of the Landsat-5 Thematic Mapper (path 197, row 31) image from 18-05-2007</gco:CharacterString>
									</gmd:description>
								</gmd:LI_Source>
							</gmd:source>
						</gmd:LI_ProcessStep>
					</gmd:processStep>
					<gmd:processStep>
						<gmd:LI_ProcessStep id="Geometric_correction_computation">
							<gmd:description>
								<gco:CharacterString>The inverse equations for the geometric corrections are computed using fit points. The obtained equations are: "X = 17655.15839212 + 0.03270074+ + -0.00644597y_ori + 0.13481079z_ori +4.05051151e-08z_ori*x_ori + -3.31578265e-08z_ori*y_ori" and "Y = -151744.91085944 + 0.00645602x_ori + 0.03271088y_ori + -0.00056158z_ori" where X and Y are row-column coordinates on the original (non geometricaly corrected) image and x_ori, y_ori and z_ori are the X,Y,Z UTM-31N-ED50 of each fitting GCP using Palà and Pons 1995 (PERS_1995_Pala_Pons) methods. Obtained RMS for fiting points are: X RMS = 0.300651; Y RMS = 0.320421 and XY RMS = 0.439387. On the other hand, the RMS values computed using test points are: X RMS = 0.592737; Y RMS = 0.482194 and XY RMS = 0.764099.</gco:CharacterString>
							</gmd:description>
							<gmd:source>
								<gmd:LI_Source id="Original_GCP_file">
									<gmd:description>
										<gco:CharacterString>GCP file (result of the GCP_digitizing process step)</gco:CharacterString>
									</gmd:description>
								</gmd:LI_Source>
							</gmd:source>
						</gmd:LI_ProcessStep>
					</gmd:processStep>
					<gmd:processStep>
						<gmd:LI_ProcessStep id="GCP_enrichment">
							<gmd:description>
								<gco:CharacterString>Enrichment of the original GCP file (Original_GCP_file) with identifier of the point (fit or test and unique identifier), X RMS of the point, Y RMS of the point, XY RMS of the point, Global fit or test X RMS (depending if the point comes from the fit or the test sets), Global fit or test Y RMS, Global fit or test XY RMS and predicted values obtained in Geometric_correction_computation process step.</gco:CharacterString>
							</gmd:description>
						</gmd:LI_ProcessStep>
					</gmd:processStep>
				</gmd:LI_Lineage>
			</gmd:lineage>
		</gmd:DQ_DataQuality>
	</gmd:dataQualityInfo>
	<gvq:dataQualityInfo>
		<gvq:GVQ_DataQuality>
			<gmd19157:scope>
				<gmd19157:DQ_Scope id="datasetScope">
					<gmd19157:level>
						<gmd:MD_ScopeCode codeList="http://www.isotc211.org/2005/resources/codeList.xml#MD_ScopeCode" codeListValue="dataset"/>
					</gmd19157:level>
					<gmd19157:extent xlink:href="#datasetExtent"/>
				</gmd19157:DQ_Scope>
			</gmd19157:scope>
			<gmd19157:report>
				<gmd19157:DQ_ThematicClassificationCorrectness id="ConfMat_test">
					<gmd19157:dateTime>
						<gco:DateTime>2013-02-26T15:41:45</gco:DateTime>
					</gmd19157:dateTime>
					<gmd19157:evaluation>
						<gvq:GVQ_SampleBasedInspection>
							<gmd19157:evaluationMethodDescription>
								<gco:CharacterString>Validation of the classification using independent test areas (25% of the buffered-MCSC, MCSC_test_12cat source)</gco:CharacterString>
							</gmd19157:evaluationMethodDescription>
							<!-- $$ when PUBLICATIONS are available: gmd19157:evaluationProcedure xlink:href="$$$$"/>
							<gmd19157:referenceDoc xlink:href="$$$$$$"/-->
							<gmd19157:evaluationMethodType>
								<gmd19157:DQ_EvaluationMethodTypeCode codeList="http://www.geoviqua.org/gmd19157/resources/codeList.xml#DQ_EvaluationMethodTypeCode" codeListValue="directExternal"/>
							</gmd19157:evaluationMethodType>
							<!-- $$ gvq:referenceDataset what is this refering to? To the dataset from where the samples are extracted i.e the buffered-MCSC? Can we define here an xllink where this source is described? But there it is described as a Ll_source! -->
							<gmd19157:samplingScheme>
								<gco:CharacterString>Random sampling with stratification into three lots (all categories included in each of the three lots) (Stratified_random_sampling process step)</gco:CharacterString>
							</gmd19157:samplingScheme>
							<gmd19157:lotDescription>
								<gco:CharacterString>Split ground truth buffered-MCSC (MCSC_reclass_buffer) into training subsample (50%, MCSC_train_12cat), test (25%, MCSC_test_12cat) and validation (25%, MCSC_test_test_12cat) subsamples using random stratified sampling methods in R software (Stratified_random_sampling process step)</gco:CharacterString>
							</gmd19157:lotDescription>
							<gmd19157:samplingRatio>
								<gco:CharacterString>100% of the test lot (MCSC_test_12cat) is inspected</gco:CharacterString>
							</gmd19157:samplingRatio>
						</gvq:GVQ_SampleBasedInspection>
					</gmd19157:evaluation>
					<gmd19157:result>
						<gmd19157:DQ_QuantitativeResult>
							<gmd19157:resultScope xlink:href="#datasetScope"/>
							<gmd19157:valueType>
								<gco:RecordType xlink:href="http://www.uncertml.org/statistics/***">Overall accuracy</gco:RecordType>
								<!-- LB: $$ which is the uncertML link for overall accurracy (percentage accuracy)? -->
								<!-- LB: $$ how we include that this is computed using only classified pixels, i.e, excluding NODATA value!? In this case, we don't have NODATA but in general this is important as the overall accuraccy computed using (or not) those nodata pixels is quite different, usually if including NODATA values results are lower. In this case those values are: 81.5% vs 80.8 % -->
							</gmd19157:valueType>
							<gmd19157:valueUnit xlink:href="urn:ogc:def:uom:UCUM:%25"/>
							<gmd19157:value>
								<gco:Record>
									<gco:Real>80.80</gco:Real>
								</gco:Record>
							</gmd19157:value>
						</gmd19157:DQ_QuantitativeResult>
					</gmd19157:result>
					<gmd19157:result>
						<gmd19157:DQ_QuantitativeResult>
							<gmd19157:resultScope xlink:href="#datasetScope"/>
							<gmd19157:valueType>
								<gco:RecordType xlink:href="http://www.uncertml.org/statistics/ConfusionMatrix">Confusion matrix recording counts from ground truthing</gco:RecordType>
							</gmd19157:valueType>
							<gmd19157:valueUnit xlink:href="urn:ogc:def:nil:OGC:inapplicable$$$$$"/>
							<!-- $$ LB: how should we define "number of pixels"? -->
							<gmd19157:value>
								<gco:Record>
								</gco:Record>
							</gmd19157:value>
						</gmd19157:DQ_QuantitativeResult>
					</gmd19157:result>
				</gmd19157:DQ_ThematicClassificationCorrectness>
			</gmd19157:report>
			<gmd19157:report>
				<gvq:GVQ_Traceability id="ConfMat_test_trace">
					<gmd19157:evaluation gco:nilReason="definedElsewhere"/>
					<gmd19157:result gco:nilReason="definedElsewhere"/>
					<gmd19157:relatedElement xlink:href="#ConfMat_test"/>
					<gvq:trace>
						<gmd19157:LI_Lineage>
							<gmd19157:source>
								<gmd19157:LI_Source id="MCSC_test_12cat">
									<gmd19157:sourceStep>
										<gmd19157:LI_ProcessStep id="MCSC_reclassification">
											<gmd19157:description>
												<gco:CharacterString>Reclassification of 233 categories (photointerpretation enables a very detailed legend) of the original MCSC into 12 categories. The choice of the classification legend is based on a simplification of MCSC product to a ground truth of 12 categories (using spectral features and biological consistency of the legend categories as main criteria)</gco:CharacterString>
												<!-- $$ can we add a discovered issue regarding the challenge of adapting the 233 classes original legend to a subjective choice of 12 categories and the difficulties on adapting a legend obtained by photointerpretation of 0.5 m resolution ortophotos to a remote sensing spatial resolution and spectral features of the land cover? this point is crucial in the global accuracy and limitations of the databases we are using in the whole study. the matching of a biologically consistent land cover classes, the spectral features and RS properties of the landsat scenes, and the photointerpreted MCSC is not easy...·· -->
											</gmd19157:description>
											<gmd19157:source>
												<gmd19157:LI_Source id="MCSC">
													<gmd19157:description>
														<gco:CharacterString>Land Cover Map of Catalonia MCSC (3rd Edition, raster format) (Mapa de Cobertes del sòl de Catalunya. 3ª Edició, model ràster) (2005-2007). Obtained from photointerpretation of 0.5 m spatial resolution ortophotographies. 233 land cover categories legend. 20m pixel size. Centre de Recerca Ecològica i Aplicacions Forestals CREAF (2007)</gco:CharacterString>
													</gmd19157:description>
													<gmd19157:sourceExtent>
														<gmd:EX_Extent>
															<gmd:temporalElement>
																<gmd:EX_TemporalExtent>
																	<gmd:extent>
																		<gml:TimePeriod gml:id="MCSC_TempEx">
																			<gml:beginPosition>2005</gml:beginPosition>
																			<gml:endPosition>2007</gml:endPosition>
																		</gml:TimePeriod>
																	</gmd:extent>
																</gmd:EX_TemporalExtent>
															</gmd:temporalElement>
														</gmd:EX_Extent>
													</gmd19157:sourceExtent>
												</gmd19157:LI_Source>
											</gmd19157:source>
										</gmd19157:LI_ProcessStep>
									</gmd19157:sourceStep>
									<gmd19157:sourceStep>
										<gmd19157:LI_ProcessStep id="Buffer_MCSC_reclass">
											<gmd19157:description>
												<gco:CharacterString>Obtain a MCSC reclassified raster file with NODATA on the border pixels between categories. The aim of this step is to assure homogeneous training areas and avoid introducing the mixtures that characterize the transition between landcover categories.</gco:CharacterString>
											</gmd19157:description>
											<gmd19157:source>
												<gmd19157:LI_Source id="MCSC_reclass">
													<gmd19157:description>
														<gco:CharacterString>Original MCSC (raster format) reclassified into 12 categories (result of the MCSC_reclassification process step)</gco:CharacterString>
													</gmd19157:description>
												</gmd19157:LI_Source>
											</gmd19157:source>
										</gmd19157:LI_ProcessStep>
									</gmd19157:sourceStep>
									<gmd19157:sourceStep>
										<gmd19157:LI_ProcessStep id="Vectorize_MCSC_reclass">
											<gmd19157:description>
												<gco:CharacterString>Vectorize the MCSC reclassified raster file (result of the MCSC_reclassification process step)</gco:CharacterString>
											</gmd19157:description>
											<gmd19157:source xlink:href="#MCSC-reclass"/>
										</gmd19157:LI_ProcessStep>
									</gmd19157:sourceStep>
									<gmd19157:sourceStep>
										<gmd19157:LI_ProcessStep id="OnekmGrid_MCSC_Vector">
											<gmd19157:description>
												<gco:CharacterString>Combination of the vectorized MCSC with a 1km grid. This partition is applied to fragment larger polygons into several smaller polygons, with the aim of selecting a % of its surface for posterior sampling purposes (training areas, test areas, validation areas subsamples). Thus, only the larger polygons are fragmentated. </gco:CharacterString>
											</gmd19157:description>
											<gmd19157:source>
												<gmd19157:LI_Source id="MCSC_vector">
													<gmd19157:description>
														<gco:CharacterString>MSCS vector (result of the Vectorize_MCSC_reclass process step)</gco:CharacterString>
													</gmd19157:description>
												</gmd19157:LI_Source>
											</gmd19157:source>
										</gmd19157:LI_ProcessStep>
									</gmd19157:sourceStep>
									<gmd19157:sourceStep>
										<gmd19157:LI_ProcessStep id="Stratified_random_sampling">
											<gmd19157:description>
												<gco:CharacterString>Finally, a stratified subsampling using a R syntax randomly assigns each gridded MCSC polygon values 1 to 3. Value 1 are training polygons (50% of the area), value 2 are test polygons (25% of the area) and value 3 are validation polygons (25% of the area). Accordingly, this layer is split into three polygon layers. One of each is combined with the MCSC reclassified raster file with NODATA on the border pixels (MCSC_reclass_buffer source) to generate three raster files with (training pixels, test pixels and validation pixels, with sources id's equal to MCSC_train_12cat, MCSC_test_12cat, MCSC_test_test_12cat). Each of these raster subsamples contain all the categories included on the legend (12 categories).</gco:CharacterString>
											</gmd19157:description>
											<gmd19157:source>
												<gmd19157:LI_Source id="MCSC_vector_grid">
													<gmd19157:description>
														<gco:CharacterString>Combination of the vectorized MCSC with a 1km grid (result of the OnekmGrid_MCSC_Vector process step)</gco:CharacterString>
													</gmd19157:description>
												</gmd19157:LI_Source>
											</gmd19157:source>
											<gmd19157:source>
												<gmd19157:LI_Source id="MCSC_reclass_buffer">
													<gmd19157:description>
														<gco:CharacterString>MCSC reclassified raster file with NODATA on the border pixels (result of the Buffer_MCSC_reclass process step)</gco:CharacterString>
													</gmd19157:description>
												</gmd19157:LI_Source>
											</gmd19157:source>
										</gmd19157:LI_ProcessStep>
									</gmd19157:sourceStep>
								</gmd19157:LI_Source>
							</gmd19157:source>
						</gmd19157:LI_Lineage>
					</gvq:trace>
				</gvq:GVQ_Traceability>
			</gmd19157:report>
			<gmd19157:report>
				<gmd19157:DQ_NonQuantitativeAttributeAccuracy id="RegLog">
					<gmd19157:dateTime>
						<gco:DateTime>2013-02-26T15:41:45</gco:DateTime>
					</gmd19157:dateTime>
					<gmd19157:evaluation>
						<gvq:GVQ_SampleBasedInspection>
							<gmd19157:evaluationMethodDescription>
								<gco:CharacterString>Spatialization of the classification success probability using independent test areas (25% of the buffered-MCSC, MCSC_test_12cat source)</gco:CharacterString>
							</gmd19157:evaluationMethodDescription>
							<gmd19157:evaluationMethodType>
								<gmd19157:DQ_EvaluationMethodTypeCode codeListValue="http://www.geoviqua.org/gmd19157/resources/codeList.xml#DQ_EvaluationMethodTypeCode" codeList="directExternal"/>
							</gmd19157:evaluationMethodType>
							<gmd19157:samplingScheme>
								<gco:CharacterString>Random sampling with stratification into three lots (all categories included in each of the three lots) (Stratified_random_sampling process step)</gco:CharacterString>
							</gmd19157:samplingScheme>
							<gmd19157:lotDescription>
								<!-- $$ Maybe from "The test lot (MCSC_test_12cat) is used to define the dependent ..." to the end of the paragpah should go on the trace report of this report? -->
								<gco:CharacterString>Split ground truth buffered-MCSC (MCSC_reclass_buffer) into training subsample (50%, MCSC_train_12cat), test (25%, MCSC_test_12cat) and validation (25%, MCSC_test_test_12cat) subsamples sing random stratified sampling methods in R software (Stratified_random_sampling process step). The test lot (MCSC_test_12cat) is used to define the dependent variable in the logistic regression model: success/failure binomial variable setting a 2 values reclassification of the overlaying of the classification product (ClsMix layer id="LC") and the test ground truth lot (MCSC_test_12cat) i.e., 1=agreement between ClsMix and MCSCtest, 0=disagreement between ClsMix and MCSCtest. Note that the overlaying of the classification product (ClsMix layer) and the test ground truth lot (MCSC_test_12cat) is actually the spatialization of the Confusion Matrix described in the previous quality report.</gco:CharacterString>
							</gmd19157:lotDescription>
							<gmd19157:samplingRatio>
								<!-- $$ Maybe from "However this procedure implies that only 25% of the ..." to the end of the paragpah should go on the trace report of this report? -->
								<gco:CharacterString>100% of the test lot (MCSC_test_12cat) is inspected. However this procedure implies that only 25% of the ground truth area is used in model fitting and then 10% of this 25% is sampled in the statistical model fitting in order to avoid spatial correlation (still 1105303 pixels analysed)</gco:CharacterString>
							</gmd19157:samplingRatio>
						</gvq:GVQ_SampleBasedInspection>
					</gmd19157:evaluation>
					<gmd19157:result>
						<gmd19157:DQ_QuantitativeResult>
							<gmd19157:resultScope xlink:href="#datasetScope"/>
							<gmd19157:valueType>
								<gco:RecordType xlink:href="http://www.uncertml.org/statistics/***">Discrete probability</gco:RecordType>
								<!-- I didn't know which statistic was this case: LB: $$ which is the uncertML link for AUC/ROC (percentage accuracy)? Where can we write the result refers to the % probability of success in the classification product category assignment? and that the success is defined by setting a threshold to the continuous % probability of success obtained by the predicted group resulting from the application of a threshold in the SPSS software: >50% is group 1 =success < 50% is group 0=failure of the logistic regression model ? Or this is inherent to the AUC test in itself?? Maybe Dan can answer this...-->
							</gmd19157:valueType>
							<gmd19157:valueUnit xlink:href="urn:ogc:def:uom:UCUM:%25"/>
							<gmd19157:value>
								<gco:Record>
									<gco:Real>74.10</gco:Real>
								</gco:Record>
							</gmd19157:value>
						</gmd19157:DQ_QuantitativeResult>
					</gmd19157:result>
					<gmd19157:result>
						<gmd19157:DQ_QuantitativeResult>
							<gmd19157:valueType>
								<gco:RecordType>Sensitivity</gco:RecordType>
							</gmd19157:valueType>
							<gmd19157:valueUnit>
								<!-- $$ per one units-->
							</gmd19157:valueUnit>
							<gmd19157:value>
								<gco:Record>0.72</gco:Record>
							</gmd19157:value>
							<!--where do we explain how specificity is calculated based on false negatives/ false positives/true negatives /true positives ratios from the AUC??? revise how it is calculated. I don't find the UncertML statistic for this case, so I don't know what to write in the gmd19157:DQ_QuantitativeResult...I jump directly to gmd19157:result -->
						</gmd19157:DQ_QuantitativeResult>
					</gmd19157:result>
					<gmd19157:result>
						<gmd19157:DQ_QuantitativeResult>
							<gmd19157:valueType>
								<gco:RecordType>Specificity</gco:RecordType>
							</gmd19157:valueType>
							<gmd19157:valueUnit>
								<!-- $$ per one units-->
							</gmd19157:valueUnit>
							<gmd19157:value>
								<gco:Record>0.76</gco:Record>
							</gmd19157:value>
							<!--where do we explain how specificity is calculated based on false negatives/ false positives/true negatives /true positives ratios from the AUC??? revise how it is calculated. I don't find the UncertML statistic for this case, so I don't know what to write in the gmd19157:DQ_QuantitativeResult...I jump directly to gmd19157:result -->
							<!--I don't know how to encode in UncertML other statistics from the logistic regression report: Nagelkerke R2 0.375, Cox&Snell R square 0.281. Can we directly hang a pdf report of the SPSS logistic regression results report output?? -->
						</gmd19157:DQ_QuantitativeResult>
					</gmd19157:result>
				</gmd19157:DQ_NonQuantitativeAttributeAccuracy>
			</gmd19157:report>
			<gmd19157:report>
				<gvq:GVQ_Traceability id="RegLog_trace">
					<gmd19157:evaluation gco:nilReason="definedElsewhere"/>
					<gmd19157:result gco:nilReason="definedElsewhere"/>
					<gmd19157:relatedElement xlink:href="#RegLog"/>
					<gvq:trace>
						<gmd19157:LI_Lineage>
							<gmd19157:processStep xlink:href="IsoMM_process"/>
							<gmd19157:processStep>
								<gmd19157:LI_ProcessStep>
									<gmd19157:description>
										<gco:CharacterString>Reclassification of the IsoMM with the statistical class values obtained in the second step (supervised classification: from the IsoMM unsupervised classification + training areas) in the hybrid classification product fidelity F, second fidelity F2, third fidelity F3, representativity R, second representativity R2, third representativity R3 obtained from the hybrid classification report (ClsMix report), and computation of entropy H, promiscuity P, uncertainty I and majority classes Q. This way pixel level values for all these variables (independent variables in regression model fitting) are obtained</gco:CharacterString>
									</gmd19157:description>
									<gmd19157:source xlink:href="IsoMM"/>
									<!-- $$ gmd19157:source><gmd19157:LI_Source id="ClsMix_report"/></gmd19157:source -->
								</gmd19157:LI_ProcessStep>
							</gmd19157:processStep>
							<gmd19157:processStep>
								<gmd19157:LI_ProcessStep>
									<gmd19157:description>
										<gco:CharacterString>MCSC test areas are overlaid to the product of the hybrid classification (ClsMix ID="LC") to check in which pixels the ground truth (MCSC) categories coincide with the categories assigned in the hybrid classification. This is the spatialization of the confusion matrix described in report 1. The resulting layer is reclassified into a binomial layer in which 1=coincidence in category (correct pixel) or 0=non coincidence in category (incorrectly classified pixel). This layer is actually the dependent variable in the logistic regression model fitting step.</gco:CharacterString>
									</gmd19157:description>
									<gmd19157:source>
										<gmd19157:LI_Source id="Combi_ClsMix_MCSCtest">
											<gmd19157:description>
												<gco:CharacterString>MCSC test areas are overlaid to the product of the hybrid classification (ClsMix ID="LC") to check in which pixels the ground truth (MCSC) categories coincide with the categories assigned in the hybrid classification.</gco:CharacterString>
											</gmd19157:description>
										</gmd19157:LI_Source>
									</gmd19157:source>
								</gmd19157:LI_ProcessStep>
							</gmd19157:processStep>
							<gmd19157:processStep>
								<gmd19157:LI_ProcessStep>
									<gmd19157:description>
										<gco:CharacterString>Logistic regression model fitting using SPSS statistical software (subsample of 10% of the dataset).Selection of model depending on goodness of fit statistics (R2 Negelkerke, Cox adjusted R2) and apply the model formula in the algebra calculator module in MiraMon GIS software.The resulting product is a pixel level probability of success (%) in the classification according to the logistic regression model (this is to say predicted probability; id="LC_Prob" coverageDescription). Note that for validation purposes, a threshold of 50% in this layer values is set to define success in the classification (above 50%) or failure in the classification (below or equal to 50%).Besides, in the SPSS software the ROC test is done (SPSS applies this same success/failure threshold for this test). The result of the ROC test states the percentage of times the model is correct other than chance (if a value above 50% is obtained, this means the correct classification is not a result of a chance success). Other statistics obtained in the ROC test are sensitivity and specificity. In our case, the ROC value is 74%. The ROC value matches the global accuracy obtained in the confusion matrix.</gco:CharacterString>
									</gmd19157:description>
								</gmd19157:LI_ProcessStep>
							</gmd19157:processStep>
						</gmd19157:LI_Lineage>
					</gvq:trace>
				</gvq:GVQ_Traceability>
			</gmd19157:report>
			<gmd19157:report>
				<gmd19157:DQ_NonQuantitativeAttributeAccuracy id="RegLog_Val">
					<gmd19157:dateTime>
						<gco:DateTime>2013-02-26T15:41:45</gco:DateTime>
					</gmd19157:dateTime>
					<gmd19157:result>
						<gmd19157:QE_CoverageResult>
							<gmd19157:resultScope xlink:href="#datasetScope"/>
							<gmd19157:spatialRepresentationType>
								<gmd:MD_SpatialRepresentationTypeCode codeList="http://www.isotc211.org/2005/resources/Codelist/gmxCodelists.xml#MD_SpatialRepresentationTypeCode" codeListValue="grid">grid</gmd:MD_SpatialRepresentationTypeCode>
							</gmd19157:spatialRepresentationType>
							<gmd19157:resultFile xlink:href="#Categorical_accuracy_study_GeoViQua_MMZ_file"/>
							<gmd19157:resultSpatialRepresentation xlink:href="#dataset_SR"/>
							<gmd19157:resultContentDescription>
								<gmd:MD_CoverageDescription>
									<gmd:attributeDescription>
										<gco:RecordType>This layer is the error model validation layer, i.e. a binomial layer representing coincidence between the values predicted by the logistic regression model and the observed values (either correct/incorrect pixels).</gco:RecordType>
									</gmd:attributeDescription>
									<gmd:contentType>
										<!-- ·$$·· LB: link to ISO EXTENDED codelist? -->
										<gmd:MD_CoverageContentTypeCode codeList="http://www.isotc211.org/2005/resources/Codelist/gmxCodelists.xml#MD_CoverageContentTypeCode" codeListValue="MD_CoverageContentTypeCode_modelResult">modelResult</gmd:MD_CoverageContentTypeCode>
									</gmd:contentType>
								</gmd:MD_CoverageDescription>
							</gmd19157:resultContentDescription>
							<gmd19157:resultFormat xlink:href="#datasetFormat"/>
						</gmd19157:QE_CoverageResult>
					</gmd19157:result>
				</gmd19157:DQ_NonQuantitativeAttributeAccuracy>
			</gmd19157:report>
			<gmd19157:report>
				<gvq:GVQ_Traceability id="RegLog_Val_trace">
					<gmd19157:evaluation gco:nilReason="definedElsewhere"/>
					<gmd19157:result gco:nilReason="definedElsewhere"/>
					<gmd19157:relatedElement xlink:href="#RegLog_Val"/>
					<gvq:trace>
						<gmd19157:LI_Lineage>
							<gmd19157:processStep>
								<gmd19157:LI_ProcessStep>
									<gmd19157:description>
										<gco:CharacterString>A selection in the LC_prob_source (is the same layer than LC_prob ID coverageDescription) layer applying the success/failure threshold to respectively above or equal 50% values and below 50% values generates a binomial layer of correctly classified/incorrectly classified pixels (this is to say predicted correct/incorrect pixels by the logistic regression model).</gco:CharacterString>
									</gmd19157:description>
									<gmd19157:source>
										<!-- $$ how to link that THIS source is one of a coverage descriptions. In fact they are exactly the same "layer" but in one place it is described as a coverageDescription and in the other as source ("two aspects" of the same thing, we could say?) -->
										<gmd19157:LI_Source id="LC_prob_source"/>
									</gmd19157:source>
								</gmd19157:LI_ProcessStep>
							</gmd19157:processStep>
							<gmd19157:processStep>
								<gmd19157:LI_ProcessStep>
									<gmd19157:description>
										<gco:CharacterString>The hybrid classification product (id="LC_source") is crossed with the third subsample of the ground truth (25% of the MCSC: validation areas, named test-test) in order to derive another layer with coinciding categories between the validation areas (ground truth) and the assigned categories in the classification product (landcover map). A reclassified binomial layers assigns value 1 to pixels in which the category coincides (correctly classified pixels) and 0 to pixels in which the category does not coincide (incorrectly classified pixels). This layer represents observed correct/incorrect pixels.</gco:CharacterString>
									</gmd19157:description>
									<gmd19157:source>
										<gmd19157:LI_Source id="MCSC_testtest_12cat"/>
									</gmd19157:source>
									<!-- TO BE DEFINED, ID = COVERAGE DESCRIPTIONS -->
									<gmd19157:source>
										<gmd19157:LI_Source id="LC_source"/>
									</gmd19157:source>
									<!-- TO BE DEFINED, ID = COVERAGE DESCRIPTIONS -->
								</gmd19157:LI_ProcessStep>
							</gmd19157:processStep>
							<gmd19157:processStep>
								<gmd19157:LI_ProcessStep>
									<gmd19157:description>
										<gco:CharacterString>The binomial layer obtained (predicted correct/incorrect pixels according to the logistic regression model) is crossed with the observed correct/incorrect pixels layer. In the resulting layer, the focus is on coincidence between predicted by the logistic regression model and observed either correct/incorrect pixels (this means that both combinations are fine: 1-1 and 0-0 in this overlaying). This layer is the validation layer. (1 999 080 number of pixels 1-1 coincident/424 893 number of pixels 0-0 coincidences, and 0-1/1-0 disagreements!. Taking into account that this validation is carried out in the 25% of the surface of the ground truth area -only where the validation subsample is available i.e. total of 2 848 866 pixels, in the end this implies a 85.08% coincidence -either in correct or incorrect pixels-)</gco:CharacterString>
									</gmd19157:description>
								</gmd19157:LI_ProcessStep>
							</gmd19157:processStep>
						</gmd19157:LI_Lineage>
					</gvq:trace>
				</gvq:GVQ_Traceability>
			</gmd19157:report>
			<gmd19157:report>
				<gmd19157:DQ_QuantitativeAttributeAccuracy id="RegLin">
					<gmd19157:dateTime>
						<gco:DateTime>2013-02-26T15:41:45</gco:DateTime>
					</gmd19157:dateTime>
					<gmd19157:result>
						<gmd19157:QE_CoverageResult>
							<gmd19157:resultScope xlink:href="#datasetScope"/>
							<gmd19157:spatialRepresentationType>
								<gmd:MD_SpatialRepresentationTypeCode codeList="http://www.isotc211.org/2005/resources/Codelist/gmxCodelists.xml#MD_SpatialRepresentationTypeCode" codeListValue="grid">grid</gmd:MD_SpatialRepresentationTypeCode>
							</gmd19157:spatialRepresentationType>
							<gmd19157:resultFile xlink:href="#Categorical_accuracy_study_GeoViQua_MMZ_file"/>
							<gmd19157:resultSpatialRepresentation xlink:href="#dataset_SR"/>
							<gmd19157:resultContentDescription>
								<gmd:MD_CoverageDescription>
									<gmd:attributeDescription>
										<gco:RecordType>Average success probability for the statistical cluster obtained from linear regression model (object level mean average success probability expressed in %)</gco:RecordType>
									</gmd:attributeDescription>
									<gmd:contentType>
										<!-- ·$$·· LB: link to ISO EXTENDED codelist? -->
										<gmd:MD_CoverageContentTypeCode codeList="http://www.isotc211.org/2005/resources/Codelist/gmxCodelists.xml#MD_CoverageContentTypeCode" codeListValue="MD_CoverageContentTypeCode_modelResult">modelResult</gmd:MD_CoverageContentTypeCode>
									</gmd:contentType>
								</gmd:MD_CoverageDescription>
							</gmd19157:resultContentDescription>
							<gmd19157:resultFormat xlink:href="#datasetFormat"/>
						</gmd19157:QE_CoverageResult>
					</gmd19157:result>
				</gmd19157:DQ_QuantitativeAttributeAccuracy>
			</gmd19157:report>
			<gmd19157:report>
				<gvq:GVQ_Traceability id="RegLin_trace">
					<gmd19157:evaluation gco:nilReason="definedElsewhere"/>
					<gmd19157:result gco:nilReason="definedElsewhere"/>
					<gmd19157:relatedElement xlink:href="#RegLin"/>
					<gvq:trace>
						<gmd19157:LI_Lineage>
							<gmd19157:processStep>
								<gmd19157:LI_ProcessStep>
									<gmd19157:description>
										<gco:CharacterString>The IsoMM (Isodata product) is the layer from which the polygons are delimited (polygons=statistical cluster). From these polygons, the weighed by area average values of the independent variables layers (F, F2, F3, R, R2, R3, H, I, P, Q) and the dependent layer (for the testing areas subsample of the MCSC boundaries of the IsoMM -Isodata product-), mean values of the pixels inside the polygons: this is to say mean of the probability of success % obtained at pixel level based on observed values for the test subsample)</gco:CharacterString>
									</gmd19157:description>
									<gmd19157:source xlink:href="#IsoMM"/> <!-- ·$$·· the dependent variable is now another layer? IsoMM adapted to the mcsc12cat_test areas; vector layer, group polygons with "ciclar.exe", combicapa with observed correct pixels from mcsc12test+clsmix: mean for each polygon -->
									<gmd19157:source>
										<gmd19157:LI_Source id="F_source"/>
									</gmd19157:source>
									<gmd19157:source>
										<gmd19157:LI_Source id="F2_source"/>
									</gmd19157:source>
									<gmd19157:source>
										<gmd19157:LI_Source id="F3_source"/>
									</gmd19157:source>
									<gmd19157:source>
										<gmd19157:LI_Source id="R_source"/>
									</gmd19157:source>
									<gmd19157:source>
										<gmd19157:LI_Source id="R2_source"/>
									</gmd19157:source>
									<gmd19157:source>
										<gmd19157:LI_Source id="R3_source"/>
									</gmd19157:source>
									<gmd19157:source>
										<gmd19157:LI_Source id="H_source"/>
									</gmd19157:source>
									<gmd19157:source>
										<gmd19157:LI_Source id="P_source"/>
									</gmd19157:source>
									<gmd19157:source>
										<gmd19157:LI_Source id="I_source"/>
									</gmd19157:source>
									<gmd19157:source>
										<gmd19157:LI_Source id="Q_source"/>
									</gmd19157:source>
								</gmd19157:LI_ProcessStep>
							</gmd19157:processStep>
							<gmd19157:processStep>
								<gmd19157:LI_ProcessStep>
									<gmd19157:description>
										<gco:CharacterString>Linear regression model fitting in SPSS software: selection of the best model based on higher adjusted determination coeficient and parsimony principle. The selected model only uses F as independent variable (Adjusted determination coeficient=0.943) $$ check uncertML/Thesaurus discussion July2013</gco:CharacterString>
									</gmd19157:description>
								</gmd19157:LI_ProcessStep>
							</gmd19157:processStep>
							<gmd19157:processStep>
								<gmd19157:LI_ProcessStep>
									<gmd19157:description>
										<gco:CharacterString>Validation of the linear regression model by replicating the process using as dependent variable the mean probability of success in the validation subsample (this is to say, the 25% test_test areas: MCSC_test_test_12cat). The obtained goodness of fit statistic Adjusted determination coeficient values is similar (0.931). Application of both models and correlation between predicted mean probability of successes (%) between both models' predictions: very similar models, and very close to 1 correlations
								</gco:CharacterString>
									</gmd19157:description>
									<gmd19157:source>
										<gmd19157:LI_Source id="RegLin_source"/>
									</gmd19157:source>
								</gmd19157:LI_ProcessStep>
							</gmd19157:processStep>
							<gmd19157:processStep>
								<gmd19157:LI_ProcessStep>
									<gmd19157:description>
										<gco:CharacterString>Application of the Linear regression model in the algebra calculator in MiraMon software: generation of the mean probability of success at polygon level. ($$$ Discovered issue: 23July: values of the RegLin model should be between 0-1? but applying the model, the values obtained are higher than 1 in 1942355 pixels!!) <!--($$$ Discovered issue: 23July: values of the RegLin model should be between 0-1? but applying the model, the values obtained are higher than 1 in 1942355 pixels!!) -->
								</gco:CharacterString>
									</gmd19157:description>
								</gmd19157:LI_ProcessStep>
							</gmd19157:processStep>
						</gmd19157:LI_Lineage>
					</gvq:trace>
				</gvq:GVQ_Traceability>
			</gmd19157:report>
			<gmd19157:lineage>
				<gmd19157:LI_Lineage>
					<gmd19157:statement>
						<!-- $$ LB: can we cite a PDF file including explanations, diagrams, etc? See XP excel-->
						<gco:CharacterString>The obtention of the hybrid classification product (ID="LC" in coverageDescription) is explained on the next processStep (****). Moreover, see the reports explaing the traces: ConfMat_test_trace, RegLog_trace, RegLin_trace for other coverageDescription's lineage.</gco:CharacterString>
					</gmd19157:statement>
					<gmd19157:processStep>
						<gmd19157:LI_ProcessStep id="IsoMM_process">
							<gmd19157:description>
								<gco:CharacterString>Unsupervised classification (Isodata algorithm) of 47 standardized bands (6dates x6bands=36 landsat bands, 1 slope map, 6 NDVIs, 4 topoclimatic variables)</gco:CharacterString>
							</gmd19157:description>
							<gmd19157:source>
								<gmd19157:LI_Source id="Landsat_NDVI_corrected_images">
									<gmd19157:description>
										<gco:CharacterString>Landsat-5 Thematic Mapper (path 197, row 31) 6 dates multitemporal set (2005-2007), 6 optical bands (30 m spatial resolution). thermal band discarded due to low spatial resolution (120m) after geometric correctected</gco:CharacterString>
									</gmd19157:description>
									<gmd19157:sourceStep>
										<gmd19157:LI_ProcessStep>
											<gmd19157:description>
												<gco:CharacterString>Geometric (Palà and Pons 1995) and radiometric corrections (Pons and Solé-Sugrañes 1994) using ASTER DEM (ERSDAC 2009), applying clouds, cloud shadows, sea and snow cover masks. Resampling to 20 m spatial resolution.Transformation to calculate NDVI (Spectral vegetation index -Rouse et al. 1973-) for each date. Bands standardization (Spiegel 1991) to avoid difference of measurement units among the bands to be introduced in the classification process.</gco:CharacterString>
											</gmd19157:description>
										</gmd19157:LI_ProcessStep>
									</gmd19157:sourceStep>
								</gmd19157:LI_Source>
							</gmd19157:source>
							<gmd19157:source>
								<gmd19157:LI_Source id="Slope_map">
									<gmd19157:description>
										<gco:CharacterString>Slope map derived from DTM based on PNOA at 5 m spatial resolution using 8 neighbours method and adapted to the 20 m resampled bands (median resolution change). This band is intended to account for the relief in terraces, abrupt or vertical slopes. Standardization of the slope maps to avoid difference of measurement units among the bands to be introduced in the classification process.</gco:CharacterString>
										<!--ask Gerard if any changes have been made to this step. I don't remember exactly..-->
									</gmd19157:description>
								</gmd19157:LI_Source>
							</gmd19157:source>
							<gmd19157:source>
								<gmd19157:LI_Source id="Topoclimatic_variables">
									<gmd19157:description>
										<gco:CharacterString>Topoclimatic variables calculated from the historical series of the Digital Climatic Atlas of Catalonia (minimum temperature of the average minimum temperature of the three coldest months, maximum temperature of the average maximum temperature of the three hotest months, minimum limiting precipitation of the three months with less precipitation, minimum solar radiation of the three months with less solar radiation). Standardization.</gco:CharacterString>
										<!--link to digital climatic atlas publication or constraints or discovered issues regarding the differences in spatial resolution, for instance??-->
									</gmd19157:description>
								</gmd19157:LI_Source>
							</gmd19157:source>
						</gmd19157:LI_ProcessStep>
					</gmd19157:processStep>
					<gmd19157:processStep>
						<gmd19157:LI_ProcessStep id="ClsMix_process">
							<gmd19157:description>
								<gco:CharacterString>Supervised classification introducing the training areas (subsample of the 50% of the MCSC: MCSC_train_12cat). Fidelity and representatitvity parameters set to 0.</gco:CharacterString>
							</gmd19157:description>
							<gmd19157:source>
								<gmd19157:LI_Source id="IsoMM">
									<gmd19157:description>
										<gco:CharacterString>IsoMM process result in 957 statistical clusters (result of the IsoMM_process process step)</gco:CharacterString>
									</gmd19157:description>
								</gmd19157:LI_Source>
							</gmd19157:source>
							<gmd19157:source>
								<gmd19157:LI_Source id="MCSC_train_12cat">
								</gmd19157:LI_Source>
							</gmd19157:source>
						</gmd19157:LI_ProcessStep>
					</gmd19157:processStep>
				</gmd19157:LI_Lineage>
			</gmd19157:lineage>
			<!-- $$  We do have a JPG file showing the lineage schema (kind of a figure in a paper). Can we cite it here (including it on the MMZ/netCDF file for example?)? -->
			<gvq:discoveredIssue>
				<!-- ··$$·· I do not find how to describe the affected Bounding Box in an "standardized" way (EX_Extent? CornerPoints)?. It is possible? Maybe the model can be extended (optional info of course) to give this information? -->
				<gvq:GVQ_DiscoveredIssue>
					<gvq:target xlink:href="#MCSC_12cat"/>
					<gvq:knownProblem>
						<gco:CharacterString>Legend choice is subjective. Some of the original 233 categories have been reclassified as nodata. In the end the % of the MCSC that has been used (with buffering) is 41.38% of the study area. Difficulties in fitting the photointerpretation product legend with a suitable spectral features legend.</gco:CharacterString>
					</gvq:knownProblem>
					<gvq:workAround>
						<gco:CharacterString>Use of the Habitats Maps of Catalonia -available online from the regional government web- to compare the categories between them and reject the most mixed ones when doubtful.</gco:CharacterString>
					</gvq:workAround>
				</gvq:GVQ_DiscoveredIssue>
			</gvq:discoveredIssue>
			<gvq:discoveredIssue>
				<!-- ··$$·· I do not find how to describe the affected Bounding Box in an "standardized" way (EX_Extent? CornerPoints)?. It is possible? Maybe the model can be extended (optional info of course) to give this information? -->
				<gvq:GVQ_DiscoveredIssue>
					<gvq:target xlink:href="#ClsMix"/>
					<gvq:knownProblem>
						<gco:CharacterString>The classification steps (both unsupervised and supervised classification steps) are affected by the selection of the multitemporal landsat scenes. In order to avoid shadows to minimize radiometric corrections loss of pixels, we have not selected scenes from November to March, and the avoidance of this period is crucial in the correct classification or distinction of broadleaved tree species and other categories. Nonetheless, the main problem in classification in Mediterranean areas is the diversity and presence of mixed forests and landcovers. </gco:CharacterString>
					</gvq:knownProblem>
					<gvq:workAround>
						<gco:CharacterString>Include autumn-winter scenes in the classification to better discriminate coniferous/deciduous species, but the most problematic is to distinguish within deciduous species (other scenes during the spring-summer period should be included, when some species have already grown leaves whether others have not yet).Consider NDVI discrimination criteria between the most problematic categories is not useful in this case because most forest landcovers are mixed forests and eventhough the broadleaved loose their leaves, other holm oaks are underneath and introduce confusion in the hybrid classification process.</gco:CharacterString>
					</gvq:workAround>
				</gvq:GVQ_DiscoveredIssue>
			</gvq:discoveredIssue>
			<gvq:discoveredIssue>
				<gvq:GVQ_DiscoveredIssue>
					<gvq:target xlink:href="#ClsMix_12cat"/>
					<gvq:knownProblem>
						<gco:CharacterString>Some methodological constraints can be defined.</gco:CharacterString>
					</gvq:knownProblem>
					<gvq:workAround>
						<gco:CharacterString>First of all be careful with legend categories (legend is always a subjective choice). The legend chosen is suited to the objectives of the present study. However, it might be unsufficient for precise ecological or botanical studies at local scales. Classification methods differ in results at pixel level, both in categories assignment and associated uncertainty. Moreover, be careful with areas with high uncertainty (checking them in the provided probabilistic maps). Spatial and temporal resolution constraint the potential usage of the product).</gco:CharacterString>
					</gvq:workAround>
				</gvq:GVQ_DiscoveredIssue>
			</gvq:discoveredIssue>
		</gvq:GVQ_DataQuality>
	</gvq:dataQualityInfo>
    <gvq:userFeedback>
    <gvq:GVQ_FeedbackCollection>
	<gvq:item>
		<gvq:userRole>
			<gvq:GVQ_UserRoleCode codeList="http://www.geoviqua.org/QualityInformationModel/4.0/resources/codeList.xml#GVQ_UserRoleCode" codeListValue=" NonresearchEndUser "/>
		</gvq:userRole>
		<gvq:user>
			<gvq:userDetails>
				<gmd:individualName>
					<gco:CharacterString>Roberto Ponte</gco:CharacterString>
				</gmd:individualName>
				<gmd:organisationName>
					<gco:CharacterString>Afrucat</gco:CharacterString>
				</gmd:organisationName>
				<gmd:contactInfo>
				</gmd:contactInfo>
				<gmd:role>
					<gmd:CI_RoleCode codeList="http://wis.wmo.int/2008/catalogues/draft_version_1-1/WMO_Codelists_ver1_1.xml#CI_RoleCode" codeListValue="user"/>
				</gmd:role>
			</gvq:userDetails>
			<gvq:applicationDomain>http://www.eionet.europa.eu/gemet/concept/3502</gvq:applicationDomain>
			<gvq:expertiseLevel>4</gvq:expertiseLevel>
			<gvq:userRole>
				<gvq:GVQ_UserRoleCode codeList="http://www.geoviqua.org/QualityInformationModel/4.0/resources/codeList.xml#GVQ_UserRoleCode" codeListValue="ResearchEndUser"/>
			</gvq:userRole>
		</gvq:user>
		<gvq:dateStamp>
			<gco:DateTime>2006-01-31T00:00:00.0Z</gco:DateTime>
		</gvq:dateStamp>
		<gvq:qualityOverride>
			<gvq:GVQ_DataQuality>
				<gmd19157:scope/>
				<gvq:discoveredIssue/>
			</gvq:GVQ_DataQuality>
		</gvq:qualityOverride>
		<gvq:userComment>
			<gvq:comment>The metadata records is beyond the expectation allowing for error traceability. Very detailed quality information.</gvq:comment>
			<gvq:mime-type>text/plain</gvq:mime-type>
		</gvq:userComment>
		<gvq:rating>
			<gvq:score>5</gvq:score>
			<gvq:justification>The data can be recommended for land cover research. The metadata records is beyond the expectation allowing for error traceability.</gvq:justification>
		</gvq:rating>
		<gvq:usage>
			<gvq:reportAspect>
				<gvq:GVQ_ReportAspectCode codeList="http://www.geoviqua.org/QualityInformationModel/4.0/resources/codeList.xml#GVQ_ReportAspectCode" codeListValue="FitnessForPurpose"/>
			</gvq:reportAspect>
			<gvq:usageDescription></gvq:usageDescription>
			<gvq:discoveredIssue>
				<gvq:GVQ_DiscoveredIssue>
					<gvq:target xlink:href="targetUID"/>
				</gvq:GVQ_DiscoveredIssue>
			</gvq:discoveredIssue>
		</gvq:usage>
	</gvq:item>
	<gvq:item>
		<gvq:userRole>
			<gvq:GVQ_UserRoleCode codeList="http://www.geoviqua.org/QualityInformationModel/4.0/resources/codeList.xml#GVQ_UserRoleCode" codeListValue=" NonresearchEndUser "/>
		</gvq:userRole>
		<gvq:user>
			<gvq:userDetails>
				<gmd:individualName>
					<gco:CharacterString>Sarah White</gco:CharacterString>
				</gmd:individualName>
				<gmd:organisationName>
					<gco:CharacterString>FAO</gco:CharacterString>
				</gmd:organisationName>
				<gmd:contactInfo>
				</gmd:contactInfo>
				<gmd:role>
					<gmd:CI_RoleCode codeList="http://wis.wmo.int/2008/catalogues/draft_version_1-1/WMO_Codelists_ver1_1.xml#CI_RoleCode" codeListValue="user"/>
				</gmd:role>
			</gvq:userDetails>
			<gvq:applicationDomain>Land Cover</gvq:applicationDomain>
			<gvq:expertiseLevel>5</gvq:expertiseLevel>
			<gvq:userRole>
				<gvq:GVQ_UserRoleCode codeList="http://www.geoviqua.org/QualityInformationModel/4.0/resources/codeList.xml#GVQ_UserRoleCode" codeListValue="ResearchEndUser"/>
			</gvq:userRole>
		</gvq:user>
		<gvq:dateStamp>
			<gco:DateTime>2006-01-31T00:00:00.0Z</gco:DateTime>
		</gvq:dateStamp>
		<gvq:qualityOverride>
			<gvq:GVQ_DataQuality>
				<gmd19157:scope/>
				<gvq:discoveredIssue/>
			</gvq:GVQ_DataQuality>
		</gvq:qualityOverride>
		<gvq:userComment>
			<gvq:comment>The dataset was used for classification of vegetation cover in the Warwickshire area, UK, in 2010 - 2012. Extremely detailed metadata record.</gvq:comment>
			<gvq:mime-type>text/plain</gvq:mime-type>
		</gvq:userComment>
		<gvq:rating>
			<gvq:score>5</gvq:score>
			<gvq:justification>The metadata records was beyond my expectation.</gvq:justification>
		</gvq:rating>
		<gvq:usage>
			<gvq:reportAspect>
				<gvq:GVQ_ReportAspectCode codeList="http://www.geoviqua.org/QualityInformationModel/4.0/resources/codeList.xml#GVQ_ReportAspectCode" codeListValue="FitnessForPurpose"/>
			</gvq:reportAspect>
			<gvq:usageDescription></gvq:usageDescription>
			<gvq:discoveredIssue>
				<gvq:GVQ_DiscoveredIssue>
					<gvq:target xlink:href="targetUID"/>
				</gvq:GVQ_DiscoveredIssue>
			</gvq:discoveredIssue>
		</gvq:usage>
	</gvq:item>
	<gvq:item>
		<gvq:userRole>
			<gvq:GVQ_UserRoleCode codeList="http://www.geoviqua.org/QualityInformationModel/4.0/resources/codeList.xml#GVQ_UserRoleCode" codeListValue=" NonresearchEndUser "/>
		</gvq:userRole>
		<gvq:user>
			<gvq:userDetails>
				<gmd:individualName>
					<gco:CharacterString>Peter Adams</gco:CharacterString>
				</gmd:individualName>
				<gmd:organisationName>
					<gco:CharacterString>DEFRA</gco:CharacterString>
				</gmd:organisationName>
				<gmd:contactInfo>
				</gmd:contactInfo>
				<gmd:role>
					<gmd:CI_RoleCode codeList="http://wis.wmo.int/2008/catalogues/draft_version_1-1/WMO_Codelists_ver1_1.xml#CI_RoleCode" codeListValue="user"/>
				</gmd:role>
			</gvq:userDetails>
			<gvq:applicationDomain>Agriculture</gvq:applicationDomain>
			<gvq:expertiseLevel>5</gvq:expertiseLevel>
			<gvq:userRole>
				<gvq:GVQ_UserRoleCode codeList="http://www.geoviqua.org/QualityInformationModel/4.0/resources/codeList.xml#GVQ_UserRoleCode" codeListValue="NonresearchEndUser"/>
			</gvq:userRole>
		</gvq:user>
		<gvq:dateStamp>
			<gco:DateTime>2006-01-31T00:00:00.0Z</gco:DateTime>
		</gvq:dateStamp>
		<gvq:qualityOverride>
			<gvq:GVQ_DataQuality>
				<gmd19157:scope/>
				<gvq:discoveredIssue/>
			</gvq:GVQ_DataQuality>
		</gvq:qualityOverride>
		<gvq:userComment>
			<gvq:comment>I used this dataset for observation of UK land use between 2000 and 2010. The data is of very high quality. Metadata record provides quality information at a pixel level.</gvq:comment>
			<gvq:mime-type>text/plain</gvq:mime-type>
		</gvq:userComment>
		<gvq:rating>
			<gvq:score>5</gvq:score>
			<gvq:justification>The dataset and metadata record are of very good quality.</gvq:justification>
		</gvq:rating>
		<gvq:usage>
			<gvq:reportAspect>
				<gvq:GVQ_ReportAspectCode codeList="http://www.geoviqua.org/QualityInformationModel/4.0/resources/codeList.xml#GVQ_ReportAspectCode" codeListValue="FitnessForPurpose"/>
			</gvq:reportAspect>
			<gvq:usageDescription></gvq:usageDescription>
			<gvq:discoveredIssue>
				<gvq:GVQ_DiscoveredIssue>
					<gvq:target xlink:href="targetUID"/>
				</gvq:GVQ_DiscoveredIssue>
			</gvq:discoveredIssue>
		</gvq:usage>
	</gvq:item>
	<gvq:item>
		<gvq:userRole>
			<gvq:GVQ_UserRoleCode codeList="http://www.geoviqua.org/QualityInformationModel/4.0/resources/codeList.xml#GVQ_UserRoleCode" codeListValue=" NonresearchEndUser "/>
		</gvq:userRole>
		<gvq:user>
			<gvq:userDetails>
				<gmd:individualName>
					<gco:CharacterString>Victor Feretti</gco:CharacterString>
				</gmd:individualName>
				<gmd:organisationName>
					<gco:CharacterString>CNR</gco:CharacterString>
				</gmd:organisationName>
				<gmd:contactInfo>
				</gmd:contactInfo>
				<gmd:role>
					<gmd:CI_RoleCode codeList="http://wis.wmo.int/2008/catalogues/draft_version_1-1/WMO_Codelists_ver1_1.xml#CI_RoleCode" codeListValue="user"/>
				</gmd:role>
			</gvq:userDetails>
			<gvq:applicationDomain>Land Cover</gvq:applicationDomain>
			<gvq:expertiseLevel>4</gvq:expertiseLevel>
			<gvq:userRole>
				<gvq:GVQ_UserRoleCode codeList="http://www.geoviqua.org/QualityInformationModel/4.0/resources/codeList.xml#GVQ_UserRoleCode" codeListValue="NonresearchEndUser"/>
			</gvq:userRole>
		</gvq:user>
		<gvq:dateStamp>
			<gco:DateTime>2006-01-31T00:00:00.0Z</gco:DateTime>
		</gvq:dateStamp>
		<gvq:qualityOverride>
			<gvq:GVQ_DataQuality>
				<gmd19157:scope/>
				<gvq:discoveredIssue/>
			</gvq:GVQ_DataQuality>
		</gvq:qualityOverride>
		<gvq:userComment>
			<gvq:comment>This dataset was used to assess vegetation cover in the south region of Italy in 2012. Uncertainty measures are available at a pixel level. The data is highly recommended for land cover applications.</gvq:comment>
			<gvq:mime-type>text/plain</gvq:mime-type>
		</gvq:userComment>
		<gvq:rating>
			<gvq:score>4</gvq:score>
			<gvq:justification>The data is suitable for land cover applications.</gvq:justification>
		</gvq:rating>
		<gvq:usage>
			<gvq:reportAspect>
				<gvq:GVQ_ReportAspectCode codeList="http://www.geoviqua.org/QualityInformationModel/4.0/resources/codeList.xml#GVQ_ReportAspectCode" codeListValue="FitnessForPurpose"/>
			</gvq:reportAspect>
			<gvq:usageDescription></gvq:usageDescription>
			<gvq:discoveredIssue>
				<gvq:GVQ_DiscoveredIssue>
					<gvq:target xlink:href="targetUID"/>
				</gvq:GVQ_DiscoveredIssue>
			</gvq:discoveredIssue>
		</gvq:usage>
	</gvq:item>
	<gvq:item>
		<gvq:userRole>
			<gvq:GVQ_UserRoleCode codeList="http://www.geoviqua.org/QualityInformationModel/4.0/resources/codeList.xml#GVQ_UserRoleCode" codeListValue=" NonresearchEndUser "/>
		</gvq:userRole>
		<gvq:user>
			<gvq:userDetails>
				<gmd:individualName>
					<gco:CharacterString>Eva Klein</gco:CharacterString>
				</gmd:individualName>
				<gmd:organisationName>
					<gco:CharacterString>Fraunhofer Institute</gco:CharacterString>
				</gmd:organisationName>
				<gmd:contactInfo>
				</gmd:contactInfo>
				<gmd:role>
					<gmd:CI_RoleCode codeList="http://wis.wmo.int/2008/catalogues/draft_version_1-1/WMO_Codelists_ver1_1.xml#CI_RoleCode" codeListValue="user"/>
				</gmd:role>
			</gvq:userDetails>
			<gvq:applicationDomain>Forestry</gvq:applicationDomain>
			<gvq:expertiseLevel>4</gvq:expertiseLevel>
			<gvq:userRole>
				<gvq:GVQ_UserRoleCode codeList="http://www.geoviqua.org/QualityInformationModel/4.0/resources/codeList.xml#GVQ_UserRoleCode" codeListValue="ResearchEndUser"/>
			</gvq:userRole>
		</gvq:user>
		<gvq:dateStamp>
			<gco:DateTime>2006-01-31T00:00:00.0Z</gco:DateTime>
		</gvq:dateStamp>
		<gvq:qualityOverride>
			<gvq:GVQ_DataQuality>
				<gmd19157:scope/>
				<gvq:discoveredIssue/>
			</gvq:GVQ_DataQuality>
		</gvq:qualityOverride>
		<gvq:userComment>
			<gvq:comment>The dataset was used to monitor changes in forest cover in Germany between 2005 and 2010. We would highly recommend this dataset for forestry and land use applications.</gvq:comment>
			<gvq:mime-type>text/plain</gvq:mime-type>
		</gvq:userComment>
		<gvq:rating>
			<gvq:score>5</gvq:score>
			<gvq:justification>The dataset is highly recommended for land cover research.</gvq:justification>
		</gvq:rating>
		<gvq:usage>
			<gvq:reportAspect>
				<gvq:GVQ_ReportAspectCode codeList="http://www.geoviqua.org/QualityInformationModel/4.0/resources/codeList.xml#GVQ_ReportAspectCode" codeListValue="FitnessForPurpose"/>
			</gvq:reportAspect>
			<gvq:usageDescription></gvq:usageDescription>
			<gvq:discoveredIssue>
				<gvq:GVQ_DiscoveredIssue>
					<gvq:target xlink:href="targetUID"/>
				</gvq:GVQ_DiscoveredIssue>
			</gvq:discoveredIssue>
		</gvq:usage>
	</gvq:item>
	<gvq:item>
		<gvq:userRole>
			<gvq:GVQ_UserRoleCode codeList="http://www.geoviqua.org/QualityInformationModel/4.0/resources/codeList.xml#GVQ_UserRoleCode" codeListValue=" ResearchEndUser "/>
		</gvq:userRole>
		<gvq:user>
			<gvq:userDetails>
				<gmd:individualName>
					<gco:CharacterString>Mark Archer</gco:CharacterString>
				</gmd:individualName>
				<gmd:organisationName>
					<gco:CharacterString>FAO</gco:CharacterString>
				</gmd:organisationName>
				<gmd:contactInfo>
				</gmd:contactInfo>
				<gmd:role>
					<gmd:CI_RoleCode codeList="http://wis.wmo.int/2008/catalogues/draft_version_1-1/WMO_Codelists_ver1_1.xml#CI_RoleCode" codeListValue="user"/>
				</gmd:role>
			</gvq:userDetails>
			<gvq:applicationDomain>Vegetataion Cover</gvq:applicationDomain>
			<gvq:expertiseLevel>4</gvq:expertiseLevel>
			<gvq:userRole>
				<gvq:GVQ_UserRoleCode codeList="http://www.geoviqua.org/QualityInformationModel/4.0/resources/codeList.xml#GVQ_UserRoleCode" codeListValue="ResearchEndUser"/>
			</gvq:userRole>
		</gvq:user>
		<gvq:dateStamp>
			<gco:DateTime>2006-01-31T00:00:00.0Z</gco:DateTime>
		</gvq:dateStamp>
		<gvq:qualityOverride>
			<gvq:GVQ_DataQuality>
				<gmd19157:scope/>
				<gvq:discoveredIssue/>
			</gvq:GVQ_DataQuality>
		</gvq:qualityOverride>
		<gvq:userComment>
			<gvq:comment>I used this dataset for monitoring changes in vegetation cover in the UK between 2000 and 2010. The data is of very high quality and quality information is available at a pixel level.</gvq:comment>
			<gvq:mime-type>text/plain</gvq:mime-type>
		</gvq:userComment>
		<gvq:rating>
			<gvq:score>5</gvq:score>
			<gvq:justification>The data is of very high quality and quality information is available at a pixel level.</gvq:justification>
		</gvq:rating>
		<gvq:usage>
			<gvq:reportAspect>
				<gvq:GVQ_ReportAspectCode codeList="http://www.geoviqua.org/QualityInformationModel/4.0/resources/codeList.xml#GVQ_ReportAspectCode" codeListValue="FitnessForPurpose"/>
			</gvq:reportAspect>
			<gvq:usageDescription></gvq:usageDescription>
			<gvq:discoveredIssue>
				<gvq:GVQ_DiscoveredIssue>
					<gvq:target xlink:href="targetUID"/>
				</gvq:GVQ_DiscoveredIssue>
			</gvq:discoveredIssue>
		</gvq:usage>
	</gvq:item>
	<gvq:item>
		<gvq:userRole>
			<gvq:GVQ_UserRoleCode codeList="http://www.geoviqua.org/QualityInformationModel/4.0/resources/codeList.xml#GVQ_UserRoleCode" codeListValue=" ResearchEndUser "/>
		</gvq:userRole>
		<gvq:user>
			<gvq:userDetails>
				<gmd:individualName>
					<gco:CharacterString>Recardo Reviero</gco:CharacterString>
				</gmd:individualName>
				<gmd:organisationName>
					<gco:CharacterString>UAB</gco:CharacterString>
				</gmd:organisationName>
				<gmd:contactInfo>
				</gmd:contactInfo>
				<gmd:role>
					<gmd:CI_RoleCode codeList="http://wis.wmo.int/2008/catalogues/draft_version_1-1/WMO_Codelists_ver1_1.xml#CI_RoleCode" codeListValue="user"/>
				</gmd:role>
			</gvq:userDetails>
			<gvq:applicationDomain>Land Cover</gvq:applicationDomain>
			<gvq:expertiseLevel>5</gvq:expertiseLevel>
			<gvq:userRole>
				<gvq:GVQ_UserRoleCode codeList="http://www.geoviqua.org/QualityInformationModel/4.0/resources/codeList.xml#GVQ_UserRoleCode" codeListValue="NonresearchEndUser"/>
			</gvq:userRole>
		</gvq:user>
		<gvq:dateStamp>
			<gco:DateTime>2006-01-31T00:00:00.0Z</gco:DateTime>
		</gvq:dateStamp>
		<gvq:qualityOverride>
			<gvq:GVQ_DataQuality>
				<gmd19157:scope/>
				<gvq:discoveredIssue/>
			</gvq:GVQ_DataQuality>
		</gvq:qualityOverride>
		<gvq:userComment>
			<gvq:comment>The dataset was used for classification of land cover in Brazil between 2000 and 2007. The dataset and metadata record are of very high quality. Quality information is available at a pixel level.</gvq:comment>
			<gvq:mime-type>text/plain</gvq:mime-type>
		</gvq:userComment>
		<gvq:rating>
			<gvq:score>4</gvq:score>
			<gvq:justification>Quality information is available at a pixel level.</gvq:justification>
		</gvq:rating>
		<gvq:usage>
			<gvq:reportAspect>
				<gvq:GVQ_ReportAspectCode codeList="http://www.geoviqua.org/QualityInformationModel/4.0/resources/codeList.xml#GVQ_ReportAspectCode" codeListValue="FitnessForPurpose"/>
			</gvq:reportAspect>
			<gvq:usageDescription></gvq:usageDescription>
			<gvq:discoveredIssue>
				<gvq:GVQ_DiscoveredIssue>
					<gvq:target xlink:href="targetUID"/>
				</gvq:GVQ_DiscoveredIssue>
			</gvq:discoveredIssue>
		</gvq:usage>
	</gvq:item>
	<gvq:item>
		<gvq:userRole>
			<gvq:GVQ_UserRoleCode codeList="http://www.geoviqua.org/QualityInformationModel/4.0/resources/codeList.xml#GVQ_UserRoleCode" codeListValue=" ResearchEndUser "/>
		</gvq:userRole>
		<gvq:user>
			<gvq:userDetails>
				<gmd:individualName>
					<gco:CharacterString>Pinar Boston</gco:CharacterString>
				</gmd:individualName>
				<gmd:organisationName>
					<gco:CharacterString>Middle East Technical University</gco:CharacterString>
				</gmd:organisationName>
				<gmd:contactInfo>
				</gmd:contactInfo>
				<gmd:role>
					<gmd:CI_RoleCode codeList="http://wis.wmo.int/2008/catalogues/draft_version_1-1/WMO_Codelists_ver1_1.xml#CI_RoleCode" codeListValue="user"/>
				</gmd:role>
			</gvq:userDetails>
			<gvq:applicationDomain>Ecosystems</gvq:applicationDomain>
			<gvq:expertiseLevel>5</gvq:expertiseLevel>
			<gvq:userRole>
				<gvq:GVQ_UserRoleCode codeList="http://www.geoviqua.org/QualityInformationModel/4.0/resources/codeList.xml#GVQ_UserRoleCode" codeListValue="ResearchEndUser"/>
			</gvq:userRole>
		</gvq:user>
		<gvq:dateStamp>
			<gco:DateTime>2006-01-31T00:00:00.0Z</gco:DateTime>
		</gvq:dateStamp>
		<gvq:qualityOverride>
			<gvq:GVQ_DataQuality>
				<gmd19157:scope/>
				<gvq:discoveredIssue/>
			</gvq:GVQ_DataQuality>
		</gvq:qualityOverride>
		<gvq:userComment>
			<gvq:comment>We used this dataset to classify vegetation cover in Turkey for the year 2011. The dataset provides very good spatial and temporal coverage.</gvq:comment>
			<gvq:mime-type>text/plain</gvq:mime-type>
		</gvq:userComment>
		<gvq:rating>
			<gvq:score>5</gvq:score>
			<gvq:justification>Quality information is available at a pixel level.</gvq:justification>
		</gvq:rating>
		<gvq:usage>
			<gvq:reportAspect>
				<gvq:GVQ_ReportAspectCode codeList="http://www.geoviqua.org/QualityInformationModel/4.0/resources/codeList.xml#GVQ_ReportAspectCode" codeListValue="FitnessForPurpose"/>
			</gvq:reportAspect>
			<gvq:usageDescription></gvq:usageDescription>
			<gvq:discoveredIssue>
				<gvq:GVQ_DiscoveredIssue>
					<gvq:target xlink:href="targetUID"/>
				</gvq:GVQ_DiscoveredIssue>
			</gvq:discoveredIssue>
		</gvq:usage>
	</gvq:item>
	<gvq:item>
		<gvq:userRole>
			<gvq:GVQ_UserRoleCode codeList="http://www.geoviqua.org/QualityInformationModel/4.0/resources/codeList.xml#GVQ_UserRoleCode" codeListValue=" ResearchEndUser "/>
		</gvq:userRole>
		<gvq:user>
			<gvq:userDetails>
				<gmd:individualName>
					<gco:CharacterString>Eva Sevilliano</gco:CharacterString>
				</gmd:individualName>
				<gmd:organisationName>
					<gco:CharacterString>UAB</gco:CharacterString>
				</gmd:organisationName>
				<gmd:contactInfo>
				</gmd:contactInfo>
				<gmd:role>
					<gmd:CI_RoleCode codeList="http://wis.wmo.int/2008/catalogues/draft_version_1-1/WMO_Codelists_ver1_1.xml#CI_RoleCode" codeListValue="user"/>
				</gmd:role>
			</gvq:userDetails>
			<gvq:applicationDomain>Landcover Research</gvq:applicationDomain>
			<gvq:expertiseLevel>4</gvq:expertiseLevel>
			<gvq:userRole>
				<gvq:GVQ_UserRoleCode codeList="http://www.geoviqua.org/QualityInformationModel/4.0/resources/codeList.xml#GVQ_UserRoleCode" codeListValue="ResearchEndUser"/>
			</gvq:userRole>
		</gvq:user>
		<gvq:dateStamp>
			<gco:DateTime>2006-01-31T00:00:00.0Z</gco:DateTime>
		</gvq:dateStamp>
		<gvq:qualityOverride>
			<gvq:GVQ_DataQuality>
				<gmd19157:scope/>
				<gvq:discoveredIssue/>
			</gvq:GVQ_DataQuality>
		</gvq:qualityOverride>
		<gvq:userComment>
			<gvq:comment>Our university used this dataset to monitor changes in the agricultural land use in Spain between 2005 and 2010. We would highly recommend this dataset for landcover research.</gvq:comment>
			<gvq:mime-type>text/plain</gvq:mime-type>
		</gvq:userComment>
		<gvq:rating>
			<gvq:score>5</gvq:score>
			<gvq:justification>Metadata record is extremely good. Quality and lineage information is available.</gvq:justification>
		</gvq:rating>
		<gvq:usage>
			<gvq:reportAspect>
				<gvq:GVQ_ReportAspectCode codeList="http://www.geoviqua.org/QualityInformationModel/4.0/resources/codeList.xml#GVQ_ReportAspectCode" codeListValue="FitnessForPurpose"/>
			</gvq:reportAspect>
			<gvq:usageDescription></gvq:usageDescription>
			<gvq:discoveredIssue>
				<gvq:GVQ_DiscoveredIssue>
					<gvq:target xlink:href="targetUID"/>
				</gvq:GVQ_DiscoveredIssue>
			</gvq:discoveredIssue>
		</gvq:usage>
	</gvq:item>
	<gvq:item>
		<gvq:userRole>
			<gvq:GVQ_UserRoleCode codeList="http://www.geoviqua.org/QualityInformationModel/4.0/resources/codeList.xml#GVQ_UserRoleCode" codeListValue=" ResearchEndUser "/>
		</gvq:userRole>
		<gvq:user>
			<gvq:userDetails>
				<gmd:individualName>
					<gco:CharacterString>Jon Wilkies</gco:CharacterString>
				</gmd:individualName>
				<gmd:organisationName>
					<gco:CharacterString>FAO</gco:CharacterString>
				</gmd:organisationName>
				<gmd:contactInfo>
				</gmd:contactInfo>
				<gmd:role>
					<gmd:CI_RoleCode codeList="http://wis.wmo.int/2008/catalogues/draft_version_1-1/WMO_Codelists_ver1_1.xml#CI_RoleCode" codeListValue="user"/>
				</gmd:role>
			</gvq:userDetails>
			<gvq:applicationDomain>Agriculture</gvq:applicationDomain>
			<gvq:expertiseLevel>4</gvq:expertiseLevel>
			<gvq:userRole>
				<gvq:GVQ_UserRoleCode codeList="http://www.geoviqua.org/QualityInformationModel/4.0/resources/codeList.xml#GVQ_UserRoleCode" codeListValue="NonresearchEndUser"/>
			</gvq:userRole>
		</gvq:user>
		<gvq:dateStamp>
			<gco:DateTime>2006-01-31T00:00:00.0Z</gco:DateTime>
		</gvq:dateStamp>
		<gvq:qualityOverride>
			<gvq:GVQ_DataQuality>
				<gmd19157:scope/>
				<gvq:discoveredIssue/>
			</gvq:GVQ_DataQuality>
		</gvq:qualityOverride>
		<gvq:userComment>
			<gvq:comment>The dataset was used to monitor farming land use in the UK between June 2010 and July 2013. Metadta record provided us with full lineage information which allowed traceability.</gvq:comment>
			<gvq:mime-type>text/plain</gvq:mime-type>
		</gvq:userComment>
		<gvq:rating>
			<gvq:score>5</gvq:score>
			<gvq:justification>The data is of very high quality. Metadata record provides full lineage information.</gvq:justification>
		</gvq:rating>
		<gvq:usage>
			<gvq:reportAspect>
				<gvq:GVQ_ReportAspectCode codeList="http://www.geoviqua.org/QualityInformationModel/4.0/resources/codeList.xml#GVQ_ReportAspectCode" codeListValue="FitnessForPurpose"/>
			</gvq:reportAspect>
			<gvq:usageDescription></gvq:usageDescription>
			<gvq:discoveredIssue>
				<gvq:GVQ_DiscoveredIssue>
					<gvq:target xlink:href="targetUID"/>
				</gvq:GVQ_DiscoveredIssue>
			</gvq:discoveredIssue>
		</gvq:usage>
	</gvq:item>
	<gvq:item>
		<gvq:userRole>
			<gvq:GVQ_UserRoleCode codeList="http://www.geoviqua.org/QualityInformationModel/4.0/resources/codeList.xml#GVQ_UserRoleCode" codeListValue=" ResearchEndUser "/>
		</gvq:userRole>
		<gvq:user>
			<gvq:userDetails>
				<gmd:individualName>
					<gco:CharacterString>Xavier Pau</gco:CharacterString>
				</gmd:individualName>
				<gmd:organisationName>
					<gco:CharacterString>UAB</gco:CharacterString>
				</gmd:organisationName>
				<gmd:contactInfo>
				</gmd:contactInfo>
				<gmd:role>
					<gmd:CI_RoleCode codeList="http://wis.wmo.int/2008/catalogues/draft_version_1-1/WMO_Codelists_ver1_1.xml#CI_RoleCode" codeListValue="user"/>
				</gmd:role>
			</gvq:userDetails>
			<gvq:applicationDomain>Land Cover</gvq:applicationDomain>
			<gvq:expertiseLevel>4</gvq:expertiseLevel>
			<gvq:userRole>
				<gvq:GVQ_UserRoleCode codeList="http://www.geoviqua.org/QualityInformationModel/4.0/resources/codeList.xml#GVQ_UserRoleCode" codeListValue="ResearchEndUser"/>
			</gvq:userRole>
		</gvq:user>
		<gvq:dateStamp>
			<gco:DateTime>2006-01-31T00:00:00.0Z</gco:DateTime>
		</gvq:dateStamp>
		<gvq:qualityOverride>
			<gvq:GVQ_DataQuality>
				<gmd19157:scope/>
				<gvq:discoveredIssue/>
			</gvq:GVQ_DataQuality>
		</gvq:qualityOverride>
		<gvq:userComment>
			<gvq:comment>The dataset was used for classification of forests cover in Spain between 2010 and 2013 . We discovered that data for June - August 2011 was missing but, apart from this, the dataset is of good quality.</gvq:comment>
			<gvq:mime-type>text/plain</gvq:mime-type>
		</gvq:userComment>
		<gvq:rating>
			<gvq:score>4</gvq:score>
			<gvq:justification>Overall, very good temporal and spatial coverage. Data is missing for Spain region between June and August 2011.</gvq:justification>
		</gvq:rating>
		<gvq:usage>
			<gvq:reportAspect>
				<gvq:GVQ_ReportAspectCode codeList="http://www.geoviqua.org/QualityInformationModel/4.0/resources/codeList.xml#GVQ_ReportAspectCode" codeListValue="FitnessForPurpose"/>
			</gvq:reportAspect>
			<gvq:usageDescription></gvq:usageDescription>
			<gvq:discoveredIssue>
				<gvq:GVQ_DiscoveredIssue>
					<gvq:target xlink:href="targetUID"/>
				</gvq:GVQ_DiscoveredIssue>
			</gvq:discoveredIssue>
		</gvq:usage>
	</gvq:item>
	</gvq:GVQ_FeedbackCollection>
	</gvq:userFeedback>
</gvq:GVQ_Metadata>