<?xml version="1.0" encoding="UTF-8"?>
<gvq:GVQ_Metadata xmlns:updated19115="http://www.geoviqua.org/19115_updates" xmlns:xlink="http://www.w3.org/1999/xlink" xmlns:xsi="http://www.w3.org/2001/XMLSchema-instance" xmlns:gmd="http://www.isotc211.org/2005/gmd" xmlns:gco="http://www.isotc211.org/2005/gco" xmlns:gvq="http://www.geoviqua.org/QualityInformationModel/3.1" xmlns:gml="http://www.opengis.net/gml/3.2" xmlns:gmd19157="http://www.geoviqua.org/gmd19157" xsi:schemaLocation="http://www.geoviqua.org/QualityInformationModel/3.1 http://schemas.geoviqua.org/GVQ/3.1.0/GeoViQua_PQM_UQM.xsd http://www.uncertml.org/2.0 http://www.uncertml.org/uncertml.xsd">
  <gmd:fileIdentifier>
      <gco:CharacterString>a0091-88fd-11da-a88f-000d939bc5d8</gco:CharacterString>
  </gmd:fileIdentifier>
  <gmd:language>
      <gco:CharacterString>eng</gco:CharacterString>
  </gmd:language>
  <gmd:characterSet>
      <gmd:MD_CharacterSetCode codeList="http://www.isotc211.org/2005/resources/codeList.xml#MD_CharacterSetCode" codeListValue="utf8"/>
  </gmd:characterSet>
  <gmd:contact>
      <gmd:CI_ResponsibleParty>
         <gmd:individualName>
            <gco:CharacterString>Danielle Courteille</gco:CharacterString>
         </gmd:individualName>
         <gmd:organisationName>
            <gco:CharacterString>FAO - UN AGL Documentation Center</gco:CharacterString>
         </gmd:organisationName>
         <gmd:role>
            <gmd:CI_RoleCode codeList="http://www.isotc211.org/2005/resources/codeList.xml#CI_RoleCode" codeListValue="custodian"/>
         </gmd:role>
      </gmd:CI_ResponsibleParty>
  </gmd:contact>
  <gmd:dateStamp>
      <gco:DateTime xmlns:srv="http://www.isotc211.org/2005/srv">2004-10-01T17:53:39</gco:DateTime>
  </gmd:dateStamp>
  <gmd:metadataStandardName>
      <gco:CharacterString xmlns:srv="http://www.isotc211.org/2005/srv">ISO 19115:2003/19139</gco:CharacterString>
  </gmd:metadataStandardName>
  <gmd:metadataStandardVersion>
      <gco:CharacterString xmlns:srv="http://www.isotc211.org/2005/srv">1.0</gco:CharacterString>
  </gmd:metadataStandardVersion>
  <gmd:identificationInfo>
      <gmd:MD_DataIdentification>
         <gmd:citation>
            <gmd:CI_Citation>
               <gmd:title>
                  <gco:CharacterString>World Atlas of Agriculture, Land Utilization and Land Cover</gco:CharacterString>
               </gmd:title>
               <gmd:date>
                  <gmd:CI_Date>
                     <gmd:date>
                        <gco:DateTime>1969-01-01</gco:DateTime>
                     </gmd:date>
                     <gmd:dateType>
                        <gmd:CI_DateTypeCode codeList="http://www.isotc211.org/2005/resources/codeList.xml#CI_DateTypeCode" codeListValue="publication"/>
                     </gmd:dateType>
                  </gmd:CI_Date>
               </gmd:date>
               <gmd:edition gco:nilReason="missing">
                  <gco:CharacterString/>
               </gmd:edition>
               <gmd:presentationForm>
                  <gmd:CI_PresentationFormCode codeList="http://www.isotc211.org/2005/resources/codeList.xml#CI_PresentationFormCode" codeListValue="mapHardcopy"/>
               </gmd:presentationForm>
            </gmd:CI_Citation>
         </gmd:citation>
         <gmd:abstract>
            <gco:CharacterString>Include:
British Isles (Plate 1) (2500000) - Denmark, Iceland and South Scandinavia (Plate 2) (2500000) - Finland and North Scandinavia (Plate 3) (2500000) - Central Europe (Plate 4) (2500000) - Northwest Europe (Plate 5) (2500000) -  Iberian Peninsula (Plate 6) (2500000) - Italian Peninsula (Plate 7)  (2500000) - Hungary, Rumania and Balkans (north. part) (Plate 8) (2500000) - Balkans (Southern part) and Asia Minor (Plate 9) (2500000) - European USSR (Northern part) (Plate 10) (5000000) -  Asiatic USSR (Northwest part) (Plate 11) (5000000) - Asiatic USSR (Northeastern part) (Plate 12) (5000000) - Asiatic USSR (Southeastern part) (Plate 13) (5000000) - Asiatic USSR (Central part) (Plate 14) (5000000) - Asiatic USSR (Southwestern part) (Plate 15) (5000000) - Asiatic USSR (southern part) (Plate 16) (5000000) - European USSR (Southern part) (Plate 17) (5000000) - Southwest  Asia (Western part) (Plate 18) (2500000) -  Arabian Peninsula (Plate 19) (5000000) - Souithwest Asia (Eastern part) (Plate 20) (5000000) - Indian Peninsula (north, part) and Southwest China (Plate 21) (5000000) - Indian Peninsula (Southern part) and Ceylon (Plate 22) (5000000) - China (Northwestern part( (Plate 23) (5000000) - China (Northeastern part) and Korea (Plate 24) (5000000) - China (Southeastern part) (Plate 25) (5000000) - Japanese islands (Plate 26) (2500000) - Southeast Asia (Mainland) (Plate 27) (5000000) - Southeast Asia: Malaysia and West Indonesia (Plate 28) (5000000) - Southeast Asia: East Indonesia, Philippines and Taiwan (Plate 29) (5000000) - New Guinea and Hawaiian islands (Plate 30) (5000000) - West Australia (Plate 32) (5000000) - Northeastern ustralia and New Hebrides Is. (Place 32) (5000000) - Southeast Australia (Plate 33) (5000000) -  New Caledonia (Plate 33) (2500000) - New Zealand, American Samoa, Tahiti, Wallis and Futuna (Plate 34) (2500000) - North America (Northern part) (Plate 35) (2500000) - South-Central Canada (Plate 36) (2500000) - Great Lakes Region (Plate 37) (2500000) - Southeast Canada and Northeast USA (Plate 38) (2500000) -  North-central USA (Plate 39) (2500000) - Southwest Canada and Northwest USA (Plate 40) (2500000) - Southwest USA (Plate 41) (2500000) - South-central USA (Western part) (Plate 42) (2500000) - South-central USA (Eastern part) (Plate 43) (2500000) - Southeast USA (Plate 44) (2500000) -  Southern USA (Plate 45) (2500000) - Mexico (Plate 46) (5000000) - Central America (Plate 47) (3000000) - Caribbean (Plate 48) (1500000) -  South America (Northern part) (Plate 49) (5000000) - South America (Northeast part) (Plate 50) (5000000) - South America (East-central part) (Plate 51) (5000000) - South America (West-central part) (Plate 52) (5000000) - South America (Southern part) (Plate 53) (5000000) - Southwest Africa (Plate 54) (5000000) - Northeast Africa, Azores and Madeira (Plate 55) (5000000) - East Africa (Northern part) (Place 56) (5000000) - Seychelles (Plate 56) (500000) - Central Africa (Northern part) (Plate 57) (5000000) -  West Africa (Plate 58) (5000000) (1500000)- Central Africa (Southern part) (Plate 59) (5000000) (1500000) - East Africa (Plate 60) (5000000) - Southern Africa and Mauritius (Plate 61) (5000000) - Mauritius, Reunion (Plate 61) (2500000)</gco:CharacterString>
         </gmd:abstract>
         <gmd:purpose gco:nilReason="missing">
            <gco:CharacterString/>
         </gmd:purpose>
         <gmd:status>
            <gmd:MD_ProgressCode codeList="http://www.isotc211.org/2005/resources/codeList.xml#MD_ProgressCode" codeListValue="historicalArchive"/>
         </gmd:status>
         <gmd:pointOfContact>
            <gmd:CI_ResponsibleParty>
               <gmd:individualName gco:nilReason="missing">
                  <gco:CharacterString/>
               </gmd:individualName>
               <gmd:role>
                  <gmd:CI_RoleCode codeList="http://www.isotc211.org/2005/resources/codeList.xml#CI_RoleCode" codeListValue="originator"/>
               </gmd:role>
            </gmd:CI_ResponsibleParty>
         </gmd:pointOfContact>
         <gmd:pointOfContact>
            <gmd:CI_ResponsibleParty>
               <gmd:organisationName>
                  <gco:CharacterString>FAO - UN AGL Documentation Center</gco:CharacterString>
               </gmd:organisationName>
               <gmd:contactInfo>
                  <gmd:CI_Contact>
                     <gmd:address>
                        <gmd:CI_Address>
                           <gmd:deliveryPoint>
                              <gco:CharacterString>Via delle Terme di Caracalla</gco:CharacterString>
                           </gmd:deliveryPoint>
                           <gmd:city>
                              <gco:CharacterString>Rome</gco:CharacterString>
                           </gmd:city>
                           <gmd:postalCode>
                              <gco:CharacterString>00100</gco:CharacterString>
                           </gmd:postalCode>
                           <gmd:country>
                              <gco:CharacterString>Italy</gco:CharacterString>
                           </gmd:country>
                           <gmd:electronicMailAddress>
                              <gco:CharacterString>AGL-Documentation-Centre@fao.org</gco:CharacterString>
                           </gmd:electronicMailAddress>
                        </gmd:CI_Address>
                     </gmd:address>
                     <gmd:hoursOfService>
                        <gco:CharacterString>8.30 - 17.00</gco:CharacterString>
                     </gmd:hoursOfService>
                  </gmd:CI_Contact>
               </gmd:contactInfo>
               <gmd:role>
                  <gmd:CI_RoleCode codeList="http://www.isotc211.org/2005/resources/codeList.xml#CI_RoleCode" codeListValue="pointOfContact"/>
               </gmd:role>
            </gmd:CI_ResponsibleParty>
         </gmd:pointOfContact>
         <gmd:descriptiveKeywords>
            <gmd:MD_Keywords>
               <gmd:keyword>
                  <gco:CharacterString>World, Agriculture, Land Use, Farmland, Forest Cover</gco:CharacterString>
               </gmd:keyword>
               <gmd:keyword>
                  <gco:CharacterString></gco:CharacterString>
               </gmd:keyword>
               <gmd:keyword>
                  <gco:CharacterString>Cultivation (extent</gco:CharacterString>
               </gmd:keyword>
               <gmd:keyword>
                  <gco:CharacterString>intensity)</gco:CharacterString>
               </gmd:keyword>
            </gmd:MD_Keywords>
         </gmd:descriptiveKeywords>
         <gmd:spatialResolution>
            <gmd:MD_Resolution>
               <gmd:equivalentScale>
                  <gmd:MD_RepresentativeFraction>
                     <gmd:denominator>
                        <gco:Integer>2500000</gco:Integer>
                     </gmd:denominator>
                  </gmd:MD_RepresentativeFraction>
               </gmd:equivalentScale>
            </gmd:MD_Resolution>
         </gmd:spatialResolution>
         <gmd:language>
            <gco:CharacterString>eng</gco:CharacterString>
         </gmd:language>
         <gmd:characterSet>
            <gmd:MD_CharacterSetCode codeList="http://www.isotc211.org/2005/resources/codeList.xml#MD_CharacterSetCode" codeListValue="utf8"/>
         </gmd:characterSet>
         <gmd:topicCategory>
            <gmd:MD_TopicCategoryCode>land use</gmd:MD_TopicCategoryCode>
         </gmd:topicCategory>
         <gmd:extent>
            <gmd:EX_Extent>
               <gmd:geographicElement>
                  <gmd:EX_GeographicBoundingBox>
                     <gmd:westBoundLongitude>
                        <gco:Decimal>-180</gco:Decimal>
                     </gmd:westBoundLongitude>
                     <gmd:eastBoundLongitude>
                        <gco:Decimal>180</gco:Decimal>
                     </gmd:eastBoundLongitude>
                     <gmd:southBoundLatitude>
                        <gco:Decimal>-90</gco:Decimal>
                     </gmd:southBoundLatitude>
                     <gmd:northBoundLatitude>
                        <gco:Decimal>90</gco:Decimal>
                     </gmd:northBoundLatitude>
                  </gmd:EX_GeographicBoundingBox>
               </gmd:geographicElement>
            </gmd:EX_Extent>
         </gmd:extent>
         <gmd:supplementalInformation>
            <gco:CharacterString>ISIS Identifier: 004572; Map type: ATLAS; Additional info: Under the aegis of the International Association of Agricultural Economists</gco:CharacterString>
         </gmd:supplementalInformation>
      </gmd:MD_DataIdentification>
  </gmd:identificationInfo>
  <gmd:distributionInfo>
      <gmd:MD_Distribution>
         <gmd:distributor>
            <gmd:MD_Distributor>
               <gmd:distributorContact>
                  <gmd:CI_ResponsibleParty>
                     <gmd:organisationName>
                        <gco:CharacterString>Committee for the World Atlas of Agriculture, International Association of Agricultural Economists; Istituto Geografico de Agostini</gco:CharacterString>
                     </gmd:organisationName>
                     <gmd:role>
                        <gmd:CI_RoleCode codeList="http://www.isotc211.org/2005/resources/codeList.xml#CI_RoleCode" codeListValue="publisher"/>
                     </gmd:role>
                  </gmd:CI_ResponsibleParty>
               </gmd:distributorContact>
               <gmd:distributionOrderProcess>
                  <gmd:MD_StandardOrderProcess>
                     <gmd:orderingInstructions>
                        <gco:CharacterString>Location of the data: FAO - AGL WORLD/ATLAS</gco:CharacterString>
                     </gmd:orderingInstructions>
                  </gmd:MD_StandardOrderProcess>
               </gmd:distributionOrderProcess>
               <gmd:distributorFormat>
                  <gmd:MD_Format>
                     <gmd:name>
                        <gco:CharacterString>No digital format</gco:CharacterString>
                     </gmd:name>
                     <gmd:version>
                        <gco:CharacterString>n.a.</gco:CharacterString>
                     </gmd:version>
                  </gmd:MD_Format>
               </gmd:distributorFormat>
            </gmd:MD_Distributor>
         </gmd:distributor>
      </gmd:MD_Distribution>
  </gmd:distributionInfo>
    <gvq:userFeedback>
    <gvq:GVQ_FeedbackCollection>
	<gvq:item>
		<gvq:userRole>
			<gvq:GVQ_UserRoleCode codeList="http://www.geoviqua.org/QualityInformationModel/4.0/resources/codeList.xml#GVQ_UserRoleCode" codeListValue=" NonresearchEndUser "/>
		</gvq:userRole>
		<gvq:user>
			<gvq:userDetails>
				<gmd:individualName>
					<gco:CharacterString>Paula Diaz</gco:CharacterString>
				</gmd:individualName>
				<gmd:organisationName>
					<gco:CharacterString>UAB</gco:CharacterString>
				</gmd:organisationName>
				<gmd:contactInfo>
				</gmd:contactInfo>
				<gmd:role>
					<gmd:CI_RoleCode codeList="http://wis.wmo.int/2008/catalogues/draft_version_1-1/WMO_Codelists_ver1_1.xml#CI_RoleCode" codeListValue="user"/>
				</gmd:role>
			</gvq:userDetails>
			<gvq:applicationDomain>Farming</gvq:applicationDomain>
			<gvq:expertiseLevel>4</gvq:expertiseLevel>
			<gvq:userRole>
				<gvq:GVQ_UserRoleCode codeList="http://www.geoviqua.org/QualityInformationModel/4.0/resources/codeList.xml#GVQ_UserRoleCode" codeListValue="NonresearchEndUser"/>
			</gvq:userRole>
		</gvq:user>
		<gvq:dateStamp>
			<gco:DateTime>2006-01-31T00:00:00.0Z</gco:DateTime>
		</gvq:dateStamp>
		<gvq:qualityOverride>
			<gvq:GVQ_DataQuality>
				<gmd19157:scope/>
				<gvq:discoveredIssue/>
			</gvq:GVQ_DataQuality>
		</gvq:qualityOverride>
		<gvq:userComment>
			<gvq:comment>The data was suitable for land use classification but metadata record is incomplete.</gvq:comment>
			<gvq:mime-type>text/plain</gvq:mime-type>
		</gvq:userComment>
		<gvq:rating>
			<gvq:score>3</gvq:score>
			<gvq:justification>Incomplete metadata record. Quality information is missing.</gvq:justification>
		</gvq:rating>
		<gvq:usage>
			<gvq:reportAspect>
				<gvq:GVQ_ReportAspectCode codeList="http://www.geoviqua.org/QualityInformationModel/4.0/resources/codeList.xml#GVQ_ReportAspectCode" codeListValue="FitnessForPurpose"/>
			</gvq:reportAspect>
			<gvq:usageDescription></gvq:usageDescription>
			<gvq:discoveredIssue>
				<gvq:GVQ_DiscoveredIssue>
					<gvq:target xlink:href="targetUID"/>
				</gvq:GVQ_DiscoveredIssue>
			</gvq:discoveredIssue>
		</gvq:usage>
	</gvq:item>
	<gvq:item>
		<gvq:userRole>
			<gvq:GVQ_UserRoleCode codeList="http://www.geoviqua.org/QualityInformationModel/4.0/resources/codeList.xml#GVQ_UserRoleCode" codeListValue=" NonresearchEndUser "/>
		</gvq:userRole>
		<gvq:user>
			<gvq:userDetails>
				<gmd:individualName>
					<gco:CharacterString>Gary Foley</gco:CharacterString>
				</gmd:individualName>
				<gmd:organisationName>
					<gco:CharacterString>EPA</gco:CharacterString>
				</gmd:organisationName>
				<gmd:contactInfo>
				</gmd:contactInfo>
				<gmd:role>
					<gmd:CI_RoleCode codeList="http://wis.wmo.int/2008/catalogues/draft_version_1-1/WMO_Codelists_ver1_1.xml#CI_RoleCode" codeListValue="user"/>
				</gmd:role>
			</gvq:userDetails>
			<gvq:applicationDomain>Land Use</gvq:applicationDomain>
			<gvq:expertiseLevel>5</gvq:expertiseLevel>
			<gvq:userRole>
				<gvq:GVQ_UserRoleCode codeList="http://www.geoviqua.org/QualityInformationModel/4.0/resources/codeList.xml#GVQ_UserRoleCode" codeListValue="NonresearchEndUser"/>
			</gvq:userRole>
		</gvq:user>
		<gvq:dateStamp>
			<gco:DateTime>2006-01-31T00:00:00.0Z</gco:DateTime>
		</gvq:dateStamp>
		<gvq:qualityOverride>
			<gvq:GVQ_DataQuality>
				<gmd19157:scope/>
				<gvq:discoveredIssue/>
			</gvq:GVQ_DataQuality>
		</gvq:qualityOverride>
		<gvq:userComment>
			<gvq:comment>The data iteslf is of good quality but metadata record is incomplete: no quality or lineage information.</gvq:comment>
			<gvq:mime-type>text/plain</gvq:mime-type>
		</gvq:userComment>
		<gvq:rating>
			<gvq:score>3</gvq:score>
			<gvq:justification>Metadata record is incomplete: no quality or lineage information.</gvq:justification>
		</gvq:rating>
		<gvq:usage>
			<gvq:reportAspect>
				<gvq:GVQ_ReportAspectCode codeList="http://www.geoviqua.org/QualityInformationModel/4.0/resources/codeList.xml#GVQ_ReportAspectCode" codeListValue="FitnessForPurpose"/>
			</gvq:reportAspect>
			<gvq:usageDescription></gvq:usageDescription>
			<gvq:discoveredIssue>
				<gvq:GVQ_DiscoveredIssue>
					<gvq:target xlink:href="targetUID"/>
				</gvq:GVQ_DiscoveredIssue>
			</gvq:discoveredIssue>
		</gvq:usage>
	</gvq:item>
	<gvq:item>
		<gvq:userRole>
			<gvq:GVQ_UserRoleCode codeList="http://www.geoviqua.org/QualityInformationModel/4.0/resources/codeList.xml#GVQ_UserRoleCode" codeListValue=" NonresearchEndUser "/>
		</gvq:userRole>
		<gvq:user>
			<gvq:userDetails>
				<gmd:individualName>
					<gco:CharacterString>Peter Hall</gco:CharacterString>
				</gmd:individualName>
				<gmd:organisationName>
					<gco:CharacterString>FAO</gco:CharacterString>
				</gmd:organisationName>
				<gmd:contactInfo>
				</gmd:contactInfo>
				<gmd:role>
					<gmd:CI_RoleCode codeList="http://wis.wmo.int/2008/catalogues/draft_version_1-1/WMO_Codelists_ver1_1.xml#CI_RoleCode" codeListValue="user"/>
				</gmd:role>
			</gvq:userDetails>
			<gvq:applicationDomain>Forestry</gvq:applicationDomain>
			<gvq:expertiseLevel>2</gvq:expertiseLevel>
			<gvq:userRole>
				<gvq:GVQ_UserRoleCode codeList="http://www.geoviqua.org/QualityInformationModel/4.0/resources/codeList.xml#GVQ_UserRoleCode" codeListValue="NonresearchEndUser"/>
			</gvq:userRole>
		</gvq:user>
		<gvq:dateStamp>
			<gco:DateTime>2006-01-31T00:00:00.0Z</gco:DateTime>
		</gvq:dateStamp>
		<gvq:qualityOverride>
			<gvq:GVQ_DataQuality>
				<gmd19157:scope/>
				<gvq:discoveredIssue/>
			</gvq:GVQ_DataQuality>
		</gvq:qualityOverride>
		<gvq:userComment>
			<gvq:comment>Metadata record is of quite bad quality.</gvq:comment>
			<gvq:mime-type>text/plain</gvq:mime-type>
		</gvq:userComment>
		<gvq:rating>
			<gvq:score>3</gvq:score>
			<gvq:justification>Metadata does not provide any quality information or guidelines on fitness for use.</gvq:justification>
		</gvq:rating>
		<gvq:usage>
			<gvq:reportAspect>
				<gvq:GVQ_ReportAspectCode codeList="http://www.geoviqua.org/QualityInformationModel/4.0/resources/codeList.xml#GVQ_ReportAspectCode" codeListValue="FitnessForPurpose"/>
			</gvq:reportAspect>
			<gvq:usageDescription>This dataset was used for classification of forest cover in the UK in 2012.</gvq:usageDescription>
			<gvq:discoveredIssue>
				<gvq:GVQ_DiscoveredIssue>
					<gvq:target xlink:href="targetUID"/>
				</gvq:GVQ_DiscoveredIssue>
			</gvq:discoveredIssue>
		</gvq:usage>
	</gvq:item>
	<gvq:item>
		<gvq:userRole>
			<gvq:GVQ_UserRoleCode codeList="http://www.geoviqua.org/QualityInformationModel/4.0/resources/codeList.xml#GVQ_UserRoleCode" codeListValue=" NonresearchEndUser "/>
		</gvq:userRole>
		<gvq:user>
			<gvq:userDetails>
				<gmd:individualName>
					<gco:CharacterString>Mike Stevens</gco:CharacterString>
				</gmd:individualName>
				<gmd:organisationName>
					<gco:CharacterString>ESA</gco:CharacterString>
				</gmd:organisationName>
				<gmd:contactInfo>
				</gmd:contactInfo>
				<gmd:role>
					<gmd:CI_RoleCode codeList="http://wis.wmo.int/2008/catalogues/draft_version_1-1/WMO_Codelists_ver1_1.xml#CI_RoleCode" codeListValue="user"/>
				</gmd:role>
			</gvq:userDetails>
			<gvq:applicationDomain>Land Cover</gvq:applicationDomain>
			<gvq:expertiseLevel>5</gvq:expertiseLevel>
			<gvq:userRole>
				<gvq:GVQ_UserRoleCode codeList="http://www.geoviqua.org/QualityInformationModel/4.0/resources/codeList.xml#GVQ_UserRoleCode" codeListValue="NonresearchEndUser"/>
			</gvq:userRole>
		</gvq:user>
		<gvq:dateStamp>
			<gco:DateTime>2006-01-31T00:00:00.0Z</gco:DateTime>
		</gvq:dateStamp>
		<gvq:qualityOverride>
			<gvq:GVQ_DataQuality>
				<gmd19157:scope/>
				<gvq:discoveredIssue/>
			</gvq:GVQ_DataQuality>
		</gvq:qualityOverride>
		<gvq:userComment>
			<gvq:comment>This dataset has high uncertainty. I would not recommend this data for land cover research.</gvq:comment>
			<gvq:mime-type>text/plain</gvq:mime-type>
		</gvq:userComment>
		<gvq:rating>
			<gvq:score>1</gvq:score>
			<gvq:justification>This data was unsuitable for classification of land and forest cover.</gvq:justification>
		</gvq:rating>
		<gvq:usage>
			<gvq:reportAspect>
				<gvq:GVQ_ReportAspectCode codeList="http://www.geoviqua.org/QualityInformationModel/4.0/resources/codeList.xml#GVQ_ReportAspectCode" codeListValue="FitnessForPurpose"/>
			</gvq:reportAspect>
			<gvq:usageDescription>I used this dataset to classify land and forest cover in South America between 2000 and 2010.</gvq:usageDescription>
			<gvq:discoveredIssue>
				<gvq:GVQ_DiscoveredIssue>
					<gvq:target xlink:href="targetUID"/>
				</gvq:GVQ_DiscoveredIssue>
			</gvq:discoveredIssue>
		</gvq:usage>
	</gvq:item>
	<gvq:item>
		<gvq:userRole>
			<gvq:GVQ_UserRoleCode codeList="http://www.geoviqua.org/QualityInformationModel/4.0/resources/codeList.xml#GVQ_UserRoleCode" codeListValue=" NonresearchEndUser "/>
		</gvq:userRole>
		<gvq:user>
			<gvq:userDetails>
				<gmd:individualName>
					<gco:CharacterString>Matheus Vieira</gco:CharacterString>
				</gmd:individualName>
				<gmd:organisationName>
					<gco:CharacterString>Brazilian National Institute for Space Research</gco:CharacterString>
				</gmd:organisationName>
				<gmd:contactInfo>
				</gmd:contactInfo>
				<gmd:role>
					<gmd:CI_RoleCode codeList="http://wis.wmo.int/2008/catalogues/draft_version_1-1/WMO_Codelists_ver1_1.xml#CI_RoleCode" codeListValue="user"/>
				</gmd:role>
			</gvq:userDetails>
			<gvq:applicationDomain>Forestry</gvq:applicationDomain>
			<gvq:expertiseLevel>5</gvq:expertiseLevel>
			<gvq:userRole>
				<gvq:GVQ_UserRoleCode codeList="http://www.geoviqua.org/QualityInformationModel/4.0/resources/codeList.xml#GVQ_UserRoleCode" codeListValue="NonresearchEndUser"/>
			</gvq:userRole>
		</gvq:user>
		<gvq:dateStamp>
			<gco:DateTime>2006-01-31T00:00:00.0Z</gco:DateTime>
		</gvq:dateStamp>
		<gvq:qualityOverride>
			<gvq:GVQ_DataQuality>
				<gmd19157:scope/>
				<gvq:discoveredIssue/>
			</gvq:GVQ_DataQuality>
		</gvq:qualityOverride>
		<gvq:userComment>
			<gvq:comment>Data for Brazil (year 2013) was good. Metadata record is incomplete.</gvq:comment>
			<gvq:mime-type>text/plain</gvq:mime-type>
		</gvq:userComment>
		<gvq:rating>
			<gvq:score>3</gvq:score>
			<gvq:justification>Incomplete metadata record.</gvq:justification>
		</gvq:rating>
		<gvq:usage>
			<gvq:reportAspect>
				<gvq:GVQ_ReportAspectCode codeList="http://www.geoviqua.org/QualityInformationModel/4.0/resources/codeList.xml#GVQ_ReportAspectCode" codeListValue="FitnessForPurpose"/>
			</gvq:reportAspect>
			<gvq:usageDescription>The dataset was used to observe forest cover in Brazil in 2013.</gvq:usageDescription>
			<gvq:discoveredIssue>
				<gvq:GVQ_DiscoveredIssue>
					<gvq:target xlink:href="targetUID"/>
				</gvq:GVQ_DiscoveredIssue>
			</gvq:discoveredIssue>
		</gvq:usage>
	</gvq:item>
	</gvq:GVQ_FeedbackCollection>
	</gvq:userFeedback>
</gvq:GVQ_Metadata>